Workbook

Sheet README
A1: HISAAB DO: Paisa Kahan Gaya? The money ledger, 2000–2026
A3: Facts as of | B3: September 2026 (the as-of month of the bank items behind the rows: 2026-09)
A4: Rows | B4: 389 measures, one per row on the Ledger sheet (2000–2026)
A5: By level | B5: Centre 128, State 261
A6: By mode | B6: Seedha Khaate Mein (distribution) 137, Rahat Kosh (relief) 95, Chunav Se Pehle (pre-election) 157
A7: Before a poll | B7: 164 rows name the election they preceded; 137 of them record the gap in days
A8: In the app | B8: https://occult-kranti.github.io/fact-duel/hisaab/#/money/ledger
A9: Corrections | B9: Report an error from the app's Rules & Sources page: https://occult-kranti.github.io/fact-duel/hisaab/#/rules
A11: About this file
A12: What it is | B12: One row per measure that handed out public money directly between 2000 and 2026: cash and in-kind transfers, relief funds and disaster money, and the budgets, bills and notifications announced before an election. For each: who announced or passed it, which party governed, the benefit, reach and cost, the poll it preceded with the gap in days and the official result, and what happened next.
A13: Sources | B13: Every row carries its own source: source_label ("Publisher — title (date)") and source_url, a page that was fetched and states the core fact. Each row is built from HISAAB DO question-bank items (bank_items), which were fact-checked against fetched pages under the edition's charter; the ledger adds no new research, and every number in a row appears in its own items. The lanes worked from Union budget speeches and Economic Surveys (indiabudget.gov.in), PRS Legislative Research budget analyses, Finance Commission reports, the Rajya Sabha Standing Committee on Home Affairs (261st report, Disaster Management), PIB and PMO releases, CAG audits (read through reports of their tabling), court records (Indian Kanoon, LiveLaw), peer-reviewed studies, and news reports. Election results are the official results as the bank states them (ECI figures, through the cited outlet).
A14: Source hosts | B14: Most cited first: indianexpress.com 61, thehindu.com 46, timesofindia.indiatimes.com 44, indiabudget.gov.in 31, newindianexpress.com 27, frontline.thehindu.com 24, prsindia.org 22, hindustantimes.com 15, pmindia.gov.in 11, indiatoday.in 10, rediff.com 9, business-standard.com 8; 51 hosts in all.
A15: How to read it | B15: governing_party is who governed at that level when the measure came (NDA or UPA for the Centre); it is not a verdict, and the counts reflect what the bank covers, not which party spends more. Costs carry their own qualifiers and are not comparable across rows: do not sum them. The two package rows (Karnataka's five guarantees, Telangana's six) overlap the rows of their parts. A "yes" in launched_is_approximate means "active by", not "launched in".
A16: Timing, not cause | B16: days_before_poll and poll_result record when a measure came and what the official result was. They do not show that the measure changed the result, and no row claims what caused an election result. Words such as "freebie" or "revdi" appear only where a row quotes whoever said them.
A17: Sheets | B17: Ledger: the rows (filter and sort freely). By year: measures per launch year by mode and level, as COUNTIFS formulas over the Ledger sheet. README: this sheet.
A19: Column | B19: Meaning
A20: id | B20: Stable id of the measure: <state code>-<measure>-<year>.
A21: launched | B21: When the measure was announced, launched or first paid, as the bank dates it (YYYY or YYYY-MM).
A22: launched_is_approximate | B22: "yes" when the bank gives no launch date: "launched" is then the earliest date it gives. Read it as "active by".
A23: year | B23: The launch year.
A24: measure | B24: Short name of the measure.
... A45: source_url | B45: A link to the fetched page that states the core fact.

Sheet Ledger
A1: id | B1: launched | C1: launched_is_approximate | D1: year | E1: measure | F1: mode | G1: mode_name | H1: level | I1: state_code | J1: state | K1: governing_party | L1: enacted_by | M1: benefit | N1: reach | O1: cost | P1: poll | Q1: poll_month | R1: days_before_poll | S1: poll_result | T1: outcome | U1: package_overlaps_parts | V1: tags | W1: bank_items | X1: play_links | Y1: source_label | Z1: source_url
A2: gj-drought-relief-2000 | B2: 2000 | D2: 2000 | E2: Drought relief works (Gujarat) | F2: relief | G2: Rahat Kosh (the relief fund) | H2: State | I2: GJ | J2: Gujarat | K2: BJP | M2: ₹10 a day per adult (₹5 per child) on relief works, capped at ₹1,000 a month per family | N2: Five lakh people on 2,500 works; 9,421 villages declared drought-hit | T2: Frontline judged the cash relief insufficient; 2.5 crore people were affected and kharif losses put at ₹4,250 crore. | V2: relief | W2: hrf201 | X2: https://occult-kranti.github.io/fact-duel/hisaab/#/q/hrf201 | Y2: Frontline — Gujarat's thirst (13 May 2000) | Z2: https://frontline.thehindu.com/environment/article30253968.ece
A3: in-11th-fc-calamity-relief-fund-2000 | B3: 2000 | D3: 2000 | E3: Calamity Relief Fund, 2000–05 (11th Finance Commission) | F3: relief | G3: Rahat Kosh (the relief fund) | H3: Centre | I3: IN | J3: India-wide (Centre) | K3: NDA | M3: State calamity funds for cyclone, drought, earthquake, fire, flood and hailstorm, paid 75:25 by Centre and states | O3: ₹11,007.59 crore over five years (Centre ₹8,255.69 crore) | T3: About 75% bigger than the 1995–2000 fund; UP’s five-year share was ₹987 crore and Goa’s under ₹7 crore. | V3: relief | W3: hrf200 | X3: https://occult-kranti.github.io/fact-duel/hisaab/#/q/hrf200 | Y3: Finance Commission of India — Report of the Eleventh Finance Commission, ch. IX and Annexure IX.1 (2000) | Z3: https://fincomindia.nic.in/asset/doc/commission-reports/11th-FC/11threport.pdf
A4: in-nccf-2000 | B4: 2000 | D4: 2000 | E4: National Calamity Contingency Fund | F4: relief | G4: Rahat Kosh (the relief fund) | H4: Centre | I4: IN | J4: India-wide (Centre) | K4: NDA | M4: A national fund for severe calamities, replacing an exhausted one, refilled by a surcharge on central taxes | O4: ₹500 crore initial corpus | T4: Sent ₹500 crore to quake-hit Gujarat in 2001 and ₹1,018 crore for the 2002 drought; folded into the NDRF from 2010-11. | V4: relief | W4: hrf001 | X4: https://occult-kranti.github.io/fact-duel/hisaab/#/q/hrf001 | Y4: Rajya Sabha Standing Committee on Home Affairs — 261st Report: Disaster Management (presented 7 Aug 2026), para 2.13.4 | Z4: https://bucketapi.rajyasabha.digital/public-bucket/uploads/committee/2026_08_21_committee_3339_976_6a881941b462a.pdf
A5: kl-treasury-curbs-2001 | B5: 2000 | C5: yes | D5: 2000 | E5: Treasury curbs before the 2001 poll (Kerala) | F5: pre-election | G5: Chunav Se Pehle (before the vote) | H5: State | I5: KL | J5: Kerala | K5: LDF | M5: Curbs on even routine treasury transactions for six months, with debt near ₹21,000 crore | P5: Kerala Assembly 2001 | Q5: 2001-05 | S5: UDF won 99 of 140 seats; LDF 40 | T5: The UDF won 99 of 140 seats; the LDF fell to 40. | V5: pre-election | W5: hpe200 | X5: https://occult-kranti.github.io/fact-duel/hisaab/#/q/hpe200 | Y5: Frontline — A record of sorts (26 May 2001) | Z5: https://frontline.thehindu.com/politics/article30250696.ece
A6: in-janashree-bima-2000 | B6: 2000-02 | D6: 2000 | E6: Janashree Bima Yojana | F6: distribution | G6: Seedha Khaate Mein (straight into the account) | H6: Centre | I6: IN | J6: India-wide (Centre) | K6: NDA | L6: Yashwant Sinha (Union Finance Minister, BJP) | M6: Group insurance for the poor: ₹20,000 natural death, ₹50,000 accidental death; BPL members pay half | N6: 289.94 lakh lives covered by Dec 2012 | T6: Merged into the Aam Admi Bima Yojana (launched 2007). | V6: distribution | W6: hdb400 | X6: https://occult-kranti.github.io/fact-duel/hisaab/#/q/hdb400 | Y6: Ministry of Finance — Union Budget 2000-01 speech, Part A: Social Security for the Poor (2000) | Z6: https://www.indiabudget.gov.in/budget_archive/ub2000-01/bs/bsa5.htm
A7: in-antyodaya-anna-yojana-2000 | B7: 2000-12 | D7: 2000 | E7: Antyodaya Anna Yojana | F7: distribution | G7: Seedha Khaate Mein (straight into the account) | H7: Centre | I7: IN | J7: India-wide (Centre) | K7: NDA | L7: Atal Bihari Vajpayee (Prime Minister, BJP) | M7: Wheat at ₹2 and rice at ₹3 a kg for the poorest families; 35 kg a month from April 2002 | N7: 1 crore families at launch; 2.5 crore by May 2005 | T7: The flat 35 kg carried into the 2013 food law; a 2026 draft bill would switch to 7 kg a person, capped at 35 kg. | V7: distribution | W7: hdb001; hdb045 | X7: https://occult-kranti.github.io/fact-duel/hisaab/#/q/hdb001 https://occult-kranti.github.io/fact-duel/hisaab/#/q/hdb045 | Y7: Dept of Food & Public Distribution, NFSA portal — Public Distribution System: Antyodaya Anna Yojana (accessed Sep 2026) | Z7: https://nfsa.gov.in/portal/PDS_page
A8: od-cyclone-shelters-2001 | B8: 2001 | D8: 2001 | E8: Cyclone shelters after the 1999 super cyclone | F8: relief | G8: Rahat Kosh (the relief fund) | H8: State | I8: OD | J8: Odisha | K8: BJD | M8: Cyclone shelters for coastal Orissa: 512 needed, money allocated for 240 | T8: Only 23 stood in March 2001 and work on 489 had not begun (Frontline). | V8: relief | W8: hrf101 | X8: https://occult-kranti.github.io/fact-duel/hisaab/#/q/hrf101 | Y8: Frontline — Some lessons from Orissa (3 Mar 2001) | Z8: https://frontline.thehindu.com/other/article30249961.ece
A9: od-mission-shakti-2001 | B9: 2001 | D9: 2001 | E9: Mission Shakti (Odisha) | F9: distribution | G9: Seedha Khaate Mein (straight into the account) | H9: State | I9: OD | J9: Odisha | K9: BJD | L9: Naveen Patnaik (Chief Minister, Odisha, BJD) | M9: Women’s self-help groups: 0% loans up to ₹3 lakh, interest subvention | N9: Over six lakh SHGs, 70 lakh women | O9: About ₹200 crore a year in interest subvention | T9: Bank credit to SHGs rose from ₹1,036 crore (2016-17) to ₹4,190 crore (2020-21). | V9: distribution | W9: hdb312 | X9: https://occult-kranti.github.io/fact-duel/hisaab/#/q/hdb312 | Y9: The Hindu — Behind the BJD's electoral successes in Odisha are women SHGs (17 Oct 2022) | Z9: https://www.thehindu.com/news/national/other-states/behind-the-bjds-electoral-successes-in-odisha-are-women-shgs/article66022675.ece
A10: gj-kutch-earthquake-doles-2001 | B10: 2001-01 | D10: 2001 | E10: Kutch earthquake cash doles | F10: relief | G10: Rahat Kosh (the relief fund) | H10: State | I10: GJ | J10: Gujarat | K10: BJP | L10: Keshubhai Patel (Chief Minister, Gujarat, BJP) | M10: Cash doles for survivors and a promised room for each of eight lakh uprooted families | T10: India Today counted 11 orders on doles in 10 days; Frontline called the relief the government’s most striking failure. Patel was replaced in Oct 2001. | V10: relief | W10: hrf100 | X10: https://occult-kranti.github.io/fact-duel/hisaab/#/q/hrf100 | Y10: India Today — Leader in paralysis (5 Mar 2001) | Z10: https://www.indiatoday.in/magazine/states/story/20010305-gujarat-cm-keshubhai-patel-fitness-to-rule-grows-after-failure-to-provide-quake-relief-775615-2001-03-04
A11: in-nccd-2001 | B11: 2001-02 | D11: 2001 | E11: National Calamity Contingent Duty | F11: relief | G11: Rahat Kosh (the relief fund) | H11: Centre | I11: IN | J11: India-wide (Centre) | K11: NDA | L11: Yashwant Sinha (Union Finance Minister, BJP) | M11: A special excise levy on tobacco to refill the national calamity fund, plus a 2% surcharge for Gujarat quake relief | T11: Still on the books in 2026: Finance Bill 2026 raised its schedule rate on chewing tobacco from 25% to 60%. | V11: relief | W11: hrf002 | X11: https://occult-kranti.github.io/fact-duel/hisaab/#/q/hrf002 | Y11: indiabudget.gov.in — Memorandum explaining the provisions in the Finance Bill, 2026 (Feb 2026) | Z11: https://www.indiabudget.gov.in/doc/memo.pdf
A12: in-sgry-2001 | B12: 2001-09 | D12: 2001 | E12: Sampoorna Grameen Rozgar Yojana | F12: distribution | G12: Seedha Khaate Mein (straight into the account) | H12: Centre | I12: IN | J12: India-wide (Centre) | K12: NDA | L12: Atal Bihari Vajpayee (Prime Minister, BJP) | M12: Rural wage work paid partly in free grain, merging two earlier schemes | O12: 50 lakh tonnes of grain allocated for year one | T12: 30.6 lakh tonnes had been authorised for release by the 2002-03 budget; grain off-take rose sharply in the 2002 drought. | V12: distribution | W12: hdb401 | X12: https://occult-kranti.github.io/fact-duel/hisaab/#/q/hdb401 | Y12: Ministry of Finance — Union Budget 2002-03 speech, Part A (2002) | Z12: https://www.indiabudget.gov.in/budget_archive/ub2002-03/bs/speech_a.htm
A13: in-mid-day-meals-order-2001 | B13: 2001-11 | D13: 2001 | E13: Cooked mid-day meals ordered (PUCL case) | F13: distribution | G13: Seedha Khaate Mein (straight into the account) | H13: Centre | I13: IN | J13: India-wide (Centre) | K13: NDA | M13: Supreme Court directed every state to serve cooked mid-day meals in primary schools within six months | T13: Compliance lagged: in August 2002 Frontline reported Jharkhand had still not complied. | V13: distribution | W13: hdb002 | X13: https://occult-kranti.github.io/fact-duel/hisaab/#/q/hdb002 | Y13: Frontline — Starving still in Jharkhand (3 Aug 2002) | Z13: https://frontline.thehindu.com/other/article30245718.ece
A14: ap-drought-relief-rice-2002 | B14: 2002 | D14: 2002 | E14: Drought relief rice under SGRY (Andhra Pradesh) | F14: relief | G14: Rahat Kosh (the relief fund) | H14: State | I14: AP | J14: Andhra Pradesh | K14: TDP | M14: State sought 2.5 million tonnes of rice for drought relief work and ₹2,373.44 crore from the NCCF | N14: 1.38 crore farm labourers lost work (govt estimate) | T14: Only 0.5 million tonnes had been released by May 2003, Frontline reported. | V14: relief | W14: hrf102 | X14: https://occult-kranti.github.io/fact-duel/hisaab/#/q/hrf102 | Y14: Frontline — Elusive relief in Andhra Pradesh (23 May 2003) | Z14: https://frontline.thehindu.com/the-nation/article30217066.ece
A15: ga-dayanand-social-security-2002 | B15: 2002 | D15: 2002 | E15: Dayanand Social Security Scheme | F15: distribution | G15: Seedha Khaate Mein (straight into the account) | H15: State | I15: GA | J15: Goa | K15: BJP | L15: Manohar Parrikar (Chief Minister, Goa, BJP) | M15: Monthly pension for senior citizens (₹2,000 + ₹500 medical in 2026); ₹4,000 for eligible widows | N15: With Griha Aadhar, close to 2.5 lakh people | O15: ₹480 crore (2026-27 budget) | T15: In Sept 2026 the CM said it would rise by at least ₹500 a month; The Goan called it a ‘poll bonanza’ before 2027. | V15: distribution | W15: hdb200 | X15: https://occult-kranti.github.io/fact-duel/hisaab/#/q/hdb200 | Y15: The Goan — Another bonanza on cards: Govt to enhance DSSS, Griha Aadhar by Rs 500 (10 Sep 2026) | Z15: https://www.thegoan.net/goa-news/another-bonanza-on-cards-govt-to-enhance-dsss-griha-aadhar-by-rs-500/153962.html
A16: in-drought-relief-2002 | B16: 2002 | D16: 2002 | E16: Drought relief 2002 | F16: relief | G16: Rahat Kosh (the relief fund) | H16: Centre | I16: IN | J16: India-wide (Centre) | K16: NDA | M16: NCCF and early calamity-fund releases, free grain for relief work, fodder by rail; a Task Force under the Deputy PM | O16: ₹1,018 crore from the NCCF; ₹1,227 crore CRF share; 27.74 lakh tonnes of free grain | T16: Grain off-take under welfare schemes rose to 5.48 million tonnes in Apr–Oct 2002 from 3.15 million a year earlier. | V16: relief | W16: hrf003; hrf004 | X16: https://occult-kranti.github.io/fact-duel/hisaab/#/q/hrf003 https://occult-kranti.github.io/fact-duel/hisaab/#/q/hrf004 | Y16: Economic Survey 2002-03, ch. 8 (Agriculture) — Box 8.1: Drought relief measures | Z16: https://www.indiabudget.gov.in/budget_archive/es2002-03/chapt2003/chap83.pdf
A17: mz-intodelhna-2002 | B17: 2002 | D17: 2002 | E17: Mizoram Intodelhna Programme | F17: distribution | G17: Seedha Khaate Mein (straight into the account) | H17: State | I17: MZ | J17: Mizoram | K17: MNF | L17: Zoramthanga (Chief Minister, Mizoram, MNF) | M17: ₹11,000 per beneficiary family, replacing the old land-use scheme | N17: 53,288 families | T17: The MNF lost the 2008 election: the Congress won 32 of 40 on a new land-use promise. | V17: distribution | W17: hdb324 | X17: https://occult-kranti.github.io/fact-duel/hisaab/#/q/hdb324 | Y17: Frontline — Playing the Piper (27 Nov 2013) | Z17: https://frontline.thehindu.com/politics/playing-the-piper/article5389646.ece
A18: rj-drought-relief-2002 | B18: 2002 | D18: 2002 | E18: Drought relief works (Rajasthan, 2002–03) | F18: relief | G18: Rahat Kosh (the relief fund) | H18: State | I18: RJ | J18: Rajasthan | K18: INC | L18: Ashok Gehlot (Chief Minister, Rajasthan, INC) | M18: Relief work for vulnerable families (cut from 15 to 10 days a month); ₹60 daily wage claimed | O18: Centre paid ₹188.82 crore for 20.80 lakh BPL families; state need ₹1,530 crore | P18: Rajasthan Assembly 2003 | Q18: 2003-12 | S18: BJP won 120 of 200; Congress lost power | T18: Frontline found wages as low as ₹15 in places; the BJP won the December 2003 poll with 120 of 200 seats. | V18: pre-election; relief | W18: hrf103; hpe150 | X18: https://occult-kranti.github.io/fact-duel/hisaab/#/q/hrf103 https://occult-kranti.github.io/fact-duel/hisaab/#/q/hpe150 | Y18: Frontline — From bad to worse in Rajasthan (9 May 2003) | Z18: https://frontline.thehindu.com/the-nation/article30216871.ece
A19: hr-farm-power-dues-waiver-2002 | B19: 2002-04 | D19: 2002 | E19: Farm power-dues waiver (Haryana) | F19: distribution | G19: Seedha Khaate Mein (straight into the account) | H19: State | I19: HR | J19: Haryana | K19: INLD | L19: Om Prakash Chautala (Chief Minister, Haryana, INLD) | M19: 75% of each farmer’s pending power dues waived, after a full waiver was promised before the 2000 poll | T19: Farmers’ protests spread; police firings in May 2002 left three dead (Frontline). | V19: distribution; pre-election | W19: hpe100 | X19: https://occult-kranti.github.io/fact-duel/hisaab/#/q/hpe100 | Y19: Frontline — Farmer power (8 Jun 2002) | Z19: https://frontline.thehindu.com/other/article30245094.ece
A20: pb-free-farm-power-suspended-2002 | B20: 2002-10 | D20: 2002 | E20: Free farm power suspended (Punjab) | F20: distribution | G20: Seedha Khaate Mein (straight into the account) | H20: State | I20: PB | J20: Punjab | K20: INC | L20: Amarinder Singh (Chief Minister, Punjab, INC) | M20: Free electricity for all farmers, extended in 1997, discontinued from October 2002 | O20: ₹7,715 crore for farm power subsidy (2026-27) | T20: Restored in November 2005 and unbroken since 2007. | V20: distribution | W20: hdb100 | X20: https://occult-kranti.github.io/fact-duel/hisaab/#/q/hdb100 | Y20: The Indian Express — Power subsidy to social security: Parkash Singh Badal, the architect of populist schemes (26 Apr 2023) | Z20: https://indianexpress.com/article/cities/chandigarh/power-subsidy-social-security-architect-populist-schemes-8576206/
A21: mp-power-purchase-2003 | B21: 2003 | D21: 2003 | E21: Power purchase before the 2003 poll (MP) | F21: pre-election | G21: Chunav Se Pehle (before the vote) | H21: State | I21: MP | J21: Madhya Pradesh | K21: INC | L21: Digvijaya Singh (Chief Minister, Madhya Pradesh, INC) | M21: Electricity bought from other states amid a serious shortage | O21: ₹40–60 crore | P21: Madhya Pradesh Assembly 2003 | Q21: 2003-12 | S21: BJP won 173 of 230 seats; Congress 38 | T21: The BJP won 173 of 230 seats; the Congress fell to 38, ending ten years in power. | V21: pre-election | W21: hpe201 | X21: https://occult-kranti.github.io/fact-duel/hisaab/#/q/hpe201 | Y21: Rediff — 'The power situation in MP is serious' (31 May 2003) | Z21: https://www.rediff.com/news/interview/inter/20030531.htm
A22: tn-drought-aid-2003 | B22: 2003 | D22: 2003 | E22: Drought aid demand (Tamil Nadu) | F22: relief | G22: Rahat Kosh (the relief fund) | H22: State | I22: TN | J22: Tamil Nadu | K22: AIADMK | M22: At least ₹2,027 crore and 9 lakh tonnes of rice sought from the Centre | T22: The Centre had given ₹228 crore by early 2003, per the Kisan Sabha; the state put crop losses at ₹5,388 crore. | V22: relief | W22: hrf104 | X22: https://occult-kranti.github.io/fact-duel/hisaab/#/q/hrf104 | Y22: Frontline — A worsening drought (28 Feb 2003) | Z22: https://frontline.thehindu.com/other/article30215779.ece
A23: in-antyodaya-expansion-2003 | B23: 2003-02 | D23: 2003 | E23: Antyodaya expanded (Budget 2003-04) | F23: distribution | G23: Seedha Khaate Mein (straight into the account) | H23: Centre | I23: IN | J23: India-wide (Centre) | K23: NDA | L23: Jaswant Singh (Union Finance Minister, BJP) | M23: Antyodaya grain for 50 lakh more families from 1 April 2003 | O23: ₹507 crore extra | T23: AAY covered 1.5 crore families by early 2004. | V23: distribution | W23: hdb003 | X23: https://occult-kranti.github.io/fact-duel/hisaab/#/q/hdb003 | Y23: indiabudget.gov.in — Budget Speech 2003-04, Jaswant Singh (Feb 2003) | Z23: https://www.indiabudget.gov.in/budget_archive/ub2003-04/bs/speecha.htm
A24: in-nccd-crude-2003 | B24: 2003-02 | D24: 2003 | E24: Calamity duty on crude oil | F24: relief | G24: Rahat Kosh (the relief fund) | H24: Centre | I24: IN | J24: India-wide (Centre) | K24: NDA | L24: Jaswant Singh (Union Finance Minister, BJP) | M24: NCCD of ₹50 a tonne on crude and 1% on yarn and vehicles, ‘limited to one year only’, after the 2002 drought | T24: Still levied on domestic crude in January 2026, over two decades on; the oil industry asked for its removal. | V24: relief | W24: hrf005 | X24: https://occult-kranti.github.io/fact-duel/hisaab/#/q/hrf005 | Y24: Economic Times — Budget 2026: Oil industry seeks abolition or review of OID cess (15 Jan 2026) | Z24: https://economictimes.indiatimes.com/industry/energy/oil-gas/budget-2026-oil-industry-seeks-abolition-or-review-of-oid-cess-on-pre-nelp-and-nomination-blocks/articleshow/126545404.cms
A25: in-universal-health-insurance-2003 | B25: 2003-02 | D25: 2003 | E25: Universal Health Insurance Scheme | F25: distribution | G25: Seedha Khaate Mein (straight into the account) | H25: Centre | I25: IN | J25: India-wide (Centre) | K25: NDA | L25: Jaswant Singh (Union Finance Minister, BJP) | M25: Hospital cover up to ₹30,000 for ₹1 a day; the Centre paid ₹100 a year of a BPL family’s premium | T25: Only 11,408 BPL families had joined by May 2004; the UPA limited it to BPL families and raised the subsidy. | V25: distribution | W25: hdb004 | X25: https://occult-kranti.github.io/fact-duel/hisaab/#/q/hdb004 | Y25: indiabudget.gov.in — Budget Speech 2003-04, Jaswant Singh (Feb 2003) | Z25: https://www.indiabudget.gov.in/budget_archive/ub2003-04/bs/speecha.htm
A26: ap-mahanadu-farm-package-2003 | B26: 2003-05 | D26: 2003 | E26: Naidu's Mahanadu farm package | F26: pre-election | G26: Chunav Se Pehle (before the vote) | H26: State | I26: AP | J26: Andhra Pradesh | K26: TDP | L26: N. Chandrababu Naidu (Chief Minister, Andhra Pradesh, TDP) | M26: ₹15,000 grant plus ₹2,500 micro-credit per farmer self-help group; interest waivers on drought-hit co-op loans | O26: ₹250 crore interest waiver + ₹94 crore penal-interest waiver | P26: Andhra Pradesh Assembly 2004 | Q26: 2004-04 | R26: 328 | S26: Congress won 185 of 294 seats; TDP 47 | T26: Congress won 185 of 294 seats in April 2004; the TDP fell to 47. | V26: distribution; pre-election | W26: hdb201 | X26: https://occult-kranti.github.io/fact-duel/hisaab/#/q/hdb201 | Y26: Times of India — Naidu's major sops for farmers (29 May 2003) | Z26: https://timesofindia.indiatimes.com/city/hyderabad/naidus-major-sops-for-farmers/articleshow/47811599.cms
A27: ka-yeshasvini-2003 | B27: 2003-06 | D27: 2003 | E27: Yeshasvini farmers’ health scheme | F27: distribution | G27: Seedha Khaate Mein (straight into the account) | H27: State | I27: KA | J27: Karnataka | K27: INC | L27: S.M. Krishna (Chief Minister, Karnataka, INC) | M27: Surgery at 74 listed hospitals for a ₹5-a-month premium | T27: 250 surgeries in the first 27 days; ₹14.25 crore collected (TOI, June 2003). | V27: distribution | W27: hdb402 | X27: https://occult-kranti.github.io/fact-duel/hisaab/#/q/hdb402 | Y27: The Times of India — Krishna moots Yeshasvini scheme for other sectors (29 Jun 2003) | Z27: https://timesofindia.indiatimes.com/city/bengaluru/krishna-moots-yeshasvini-scheme-for-other-sectors/articleshow/49404.cms
A28: in-india-shining-ads-2004 | B28: 2004 | D28: 2004 | E28: ‘India Shining’ government ads | F28: pre-election | G28: Chunav Se Pehle (before the vote) | H28: Centre | I28: IN | J28: India-wide (Centre) | K28: NDA | M28: A government-funded advertising campaign | O28: ₹65 crore | P28: Lok Sabha 2004 | Q28: 2004-04 | S28: INC 145, BJP 138 seats; the Congress-led UPA formed the government | T28: The EC barred its broadcast until polling ended; the NDA lost office (Congress 145, BJP 138). | V28: pre-election | W28: hpe001 | X28: https://occult-kranti.github.io/fact-duel/hisaab/#/q/hpe001 | Y28: Rediff (Reuters) — The man behind 'India Shining' slogan (2 Apr 2004) | Z28: https://www.rediff.com/business/special/shining/20040402.htm
A29: ka-farm-distress-compensation-2004 | B29: 2004 | D29: 2004 | E29: Farm-distress compensation (Karnataka) | F29: relief | G29: Rahat Kosh (the relief fund) | H29: State | I29: KA | J29: Karnataka | K29: INC | L29: S.M. Krishna (Chief Minister, Karnataka, INC) | M29: ₹1 lakh to families of indebted farmers who died by suicide | P29: Karnataka Assembly 2004 | Q29: 2004-04 | S29: Hung: BJP 79, Congress 65, JD(S) 58 of 224 | T29: Barely 10% of needy families were paid, Frontline found; the poll gave a hung House (BJP 79, Congress 65, JD(S) 58). | V29: pre-election; relief | W29: hpe102 | X29: https://occult-kranti.github.io/fact-duel/hisaab/#/q/hpe102 | Y29: Frontline — The rural anger in Karnataka (18 Jun 2004) | Z29: https://frontline.thehindu.com/cover-story/article30223009.ece
A30: in-mini-budget-2004 | B30: 2004-01 | D30: 2004 | E30: Jaswant Singh’s ‘mini-budget’ | F30: pre-election | G30: Chunav Se Pehle (before the vote) | H30: Centre | I30: IN | J30: India-wide (Centre) | K30: NDA | L30: Jaswant Singh (Union Finance Minister, BJP) | M30: Customs cuts on phones, IT and electronics; travel tax abolished | P30: Lok Sabha 2004 | Q30: 2004-04 | R30: 103 | S30: INC 145, BJP 138 seats; the Congress-led UPA formed the government | T30: Polling began 103 days later; the NDA lost office as the Congress won 145 seats to the BJP’s 138. | V30: pre-election | W30: hpe002 | X30: https://occult-kranti.github.io/fact-duel/hisaab/#/q/hpe002 | Y30: Rediff — Markets likely to zoom up on Friday (8 Jan 2004) | Z30: https://www.rediff.com/business/report/bud12/20040108.htm
A31: in-antyodaya-expansion-2004 | B31: 2004-02 | D31: 2004 | E31: Antyodaya expanded to 2 crore families (interim budget) | F31: pre-election | G31: Chunav Se Pehle (before the vote) | H31: Centre | I31: IN | J31: India-wide (Centre) | K31: NDA | L31: Jaswant Singh (Union Finance Minister, BJP) | M31: Antyodaya extended to 2 crore BPL families from 1 April 2004 | P31: Lok Sabha 2004 | Q31: 2004-04 | R31: 77 | S31: INC 145, BJP 138 seats; the Congress-led UPA formed the government | T31: The NDA lost the poll; the UPA kept the expansion (subsidy near ₹3,500 crore) and took AAY to 2.5 crore households in 2005. | V31: distribution; pre-election | W31: hdb005 | X31: https://occult-kranti.github.io/fact-duel/hisaab/#/q/hdb005 | Y31: indiabudget.gov.in — Interim Budget Speech 2004-05, Jaswant Singh (3 Feb 2004) | Z31: https://www.indiabudget.gov.in/budget_archive/ub2004-05(I)/bs/speecha.htm
A32: in-da-merger-2004 | B32: 2004-02 | D32: 2004 | E32: DA merged into basic pay (interim budget) | F32: pre-election | G32: Chunav Se Pehle (before the vote) | H32: Centre | I32: IN | J32: India-wide (Centre) | K32: NDA | L32: Jaswant Singh (Union Finance Minister, BJP) | M32: Dearness allowance up to 50% of pay merged into basic pay for central staff; ₹25,000 crore defence fund | P32: Lok Sabha 2004 | Q32: 2004-04 | R32: 77 | S32: INC 145, BJP 138 seats; the Congress-led UPA formed the government | T32: Polling began 77 days later; the NDA left office. | V32: pre-election | W32: hpe003 | X32: https://occult-kranti.github.io/fact-duel/hisaab/#/q/hpe003 | Y32: indiabudget.gov.in — Interim Budget 2004-05 speech, Jaswant Singh (3 Feb 2004) | Z32: https://www.indiabudget.gov.in/budget_archive/ub2004-05(I)/bs/speecha.htm
A33: in-farm-income-insurance-2004 | B33: 2004-02 | D33: 2004 | E33: Farm Income Insurance Scheme extended | F33: pre-election | G33: Chunav Se Pehle (before the vote) | H33: Centre | I33: IN | J33: India-wide (Centre) | K33: NDA | L33: Jaswant Singh (Union Finance Minister, BJP) | M33: Pilot extended from 20 to 100 districts; Kisan Credit Cards for all eligible farmers | P33: Lok Sabha 2004 | Q33: 2004-04 | R33: 77 | S33: INC 145, BJP 138 seats; the Congress-led UPA formed the government | T33: The pilot was discontinued in 2004 after the NDA lost the poll. | V33: pre-election | W33: hpe005 | X33: https://occult-kranti.github.io/fact-duel/hisaab/#/q/hpe005 | Y33: indiabudget.gov.in — Interim Budget 2004-05 speech, Jaswant Singh (3 Feb 2004) | Z33: https://www.indiabudget.gov.in/budget_archive/ub2004-05(I)/bs/speecha.htm
A34: in-pmssy-aiims-2004 | B34: 2004-02 | D34: 2004 | E34: Six AIIMS-like hospitals (PMSSY) | F34: pre-election | G34: Chunav Se Pehle (before the vote) | H34: Centre | I34: IN | J34: India-wide (Centre) | K34: NDA | L34: Atal Bihari Vajpayee (Prime Minister, BJP); Jaswant Singh (Union Finance Minister, BJP) | M34: Six AIIMS-like institutes at Bhopal, Bhubaneswar, Jodhpur, Patna, Raipur and Rishikesh | P34: Lok Sabha 2004 | Q34: 2004-04 | R34: 77 | S34: INC 145, BJP 138 seats; the Congress-led UPA formed the government | T34: The UPA Cabinet approved them in 2006 and MBBS classes began in 2012; a 2019 CAG report found infrastructure still pending. | V34: pre-election | W34: hpe004 | X34: https://occult-kranti.github.io/fact-duel/hisaab/#/q/hpe004 | Y34: Alt News — Did UPA govt build only one AIIMS during their tenure? (25 Apr 2021) | Z34: https://www.altnews.in/did-upa-govt-build-only-one-aiims-institute-during-their-tenure-false-claim-viral/
A35: ap-free-farm-power-2004 | B35: 2004-05 | D35: 2004 | E35: Free farm power and bill waiver (Andhra Pradesh) | F35: distribution | G35: Seedha Khaate Mein (straight into the account) | H35: State | I35: AP | J35: Andhra Pradesh | K35: INC | L35: Y.S. Rajasekhara Reddy (Chief Minister, Andhra Pradesh, INC) | M35: Free power for all farmers plus a waiver of unpaid farm power bills, signed on oath day | O35: Up to ₹436 crore in 2004-05, plus ₹1,192 crore of waived dues | T35: YSR said free power would continue while the Congress held office; the Congress was re-elected in 2009 with 156 of 294 seats. | V35: distribution | W35: hdb202 | X35: https://occult-kranti.github.io/fact-duel/hisaab/#/q/hdb202 | Y35: Times of India — Farmers to get free power (15 May 2004) | Z35: https://timesofindia.indiatimes.com/city/hyderabad/farmers-to-get-free-power/articleshow/676611.cms
A36: tn-power-tariff-rollback-2004 | B36: 2004-05 | D36: 2004 | E36: Domestic power tariff rollback (Tamil Nadu) | F36: distribution | G36: Seedha Khaate Mein (straight into the account) | H36: State | I36: TN | J36: Tamil Nadu | K36: AIADMK | L36: J. Jayalalithaa (Chief Minister, Tamil Nadu, AIADMK) | M36: Household power bills cut back to December 2001 rates | N36: Nearly 1.2 crore families | O36: ₹910 crore a year | T36: Came weeks after the DMK-led alliance swept all 39 Lok Sabha seats; paid to the TNEB as a budget subsidy. | V36: distribution | W36: hdb204 | X36: https://occult-kranti.github.io/fact-duel/hisaab/#/q/hdb204 | Y36: Times of India — Jaya on a roll: Power rates go back 2 yrs (1 Jun 2004) | Z36: https://timesofindia.indiatimes.com/india/jaya-on-a-roll-power-rates-go-back-2-yrs/articleshow/711517.cms
A37: br-floods-crf-2004 | B37: 2004-07 | D37: 2004 | E37: Bihar floods: Calamity Relief Fund release | F37: relief | G37: Rahat Kosh (the relief fund) | H37: State | I37: BR | J37: Bihar | K37: RJD | M37: First instalment of Bihar’s ₹81.8 crore CRF held up; ₹30.525 crore released on 12 July | N37: Over a crore people in 16 districts affected (unconfirmed reports) | T37: The release was delayed because the state had not filed its 2003-04 utilisation report; an inter-ministerial team assessed damage later. | V37: relief | W37: hrf202 | X37: https://occult-kranti.github.io/fact-duel/hisaab/#/q/hrf202 | Y37: Frontline — Battling Bihar (13 Aug 2004) | Z37: https://frontline.thehindu.com/other/article30223930.ece
A38: in-food-for-work-2004 | B38: 2004-07 | D38: 2004 | E38: National Food for Work Programme | F38: distribution | G38: Seedha Khaate Mein (straight into the account) | H38: Centre | I38: IN | J38: India-wide (Centre) | K38: UPA | L38: P. Chidambaram (Union Finance Minister, INC) | M38: Food-for-work in the 150 most backward districts pending a jobs-guarantee law | O38: Over ₹6,000 crore pooled from existing schemes | T38: The promised guarantee law, NREGA, was enacted in 2005 and rolled out in February 2006. | V38: distribution | W38: hdb006 | X38: https://occult-kranti.github.io/fact-duel/hisaab/#/q/hdb006 | Y38: indiabudget.gov.in — Budget Speech 2004-05, P. Chidambaram (8 Jul 2004) | Z38: https://www.indiabudget.gov.in/budget_archive/ub2004-05/bs/speecha.htm
A39: mh-free-farm-power-2004 | B39: 2004-08 | D39: 2004 | E39: Free farm power before the 2004 poll (Maharashtra) | F39: pre-election | G39: Chunav Se Pehle (before the vote) | H39: State | I39: MH | J39: Maharashtra | K39: INC | L39: Sushilkumar Shinde (Chief Minister, Maharashtra, INC) | M39: Free power for farmers, sought only from July 2004 to March 2005 | N39: Over 23 lakh farmers | O39: ₹1,590 crore subsidy | P39: Maharashtra Assembly 2004 | Q39: 2004-10 | R39: 70 | S39: Congress–NCP front retained power: NCP 71, Congress 69 of 288 seats | T39: The Congress–NCP front kept power; its March 2005 budget said it would reconsider this ‘pre-election promise’. | V39: distribution; pre-election | W39: hdb203 | X39: https://occult-kranti.github.io/fact-duel/hisaab/#/q/hdb203 | Y39: Times of India — Free power for farmers only up to March? (16 Aug 2004) | Z39: https://timesofindia.indiatimes.com/city/pune/free-power-for-farmers-only-up-to-march/articleshow/816832.cms
A40: hr-old-age-allowance-2004 | B40: 2004-11 | D40: 2004 | E40: Old Age Samman Allowance raised to ₹300 | F40: pre-election | G40: Chunav Se Pehle (before the vote) | H40: State | I40: HR | J40: Haryana | K40: INLD | L40: Om Prakash Chautala (Chief Minister, Haryana, INLD) | M40: Old-age allowance raised from ₹200 to ₹300 a month | P40: Haryana Assembly 2005 | Q40: 2005-02 | R40: 94 | S40: Congress won 67 of 90 seats; INLD 9 | T40: The INLD lost the February 2005 poll: the Congress won 67 of 90 seats and the INLD fell to 9. | V40: distribution; pre-election | W40: hdb101 | X40: https://occult-kranti.github.io/fact-duel/hisaab/#/q/hdb101 | Y40: Government of Haryana, Social Justice & Empowerment — Old Age Samman Allowance Scheme (rate history, updated Jul 2026) | Z40: https://socialjusticehry.gov.in/old-age-samman-allowance-scheme/
A41: in-foreign-disaster-aid-policy-2004 | B41: 2004-12 | D41: 2004 | E41: Foreign disaster aid declined (policy) | F41: relief | G41: Rahat Kosh (the relief fund) | H41: Centre | I41: IN | J41: India-wide (Centre) | K41: UPA | L41: Manmohan Singh (Prime Minister, INC) | M41: After the 2004 tsunami India chose to cope without foreign-government aid; NRI and charity money still allowed | T41: Offers were declined for Kashmir, Uttarakhand, J&K and Kerala until India accepted Covid aid from about 40 countries in April 2021. | V41: relief | W41: hrf006; hrf032; hrf024 | X41: https://occult-kranti.github.io/fact-duel/hisaab/#/q/hrf006 https://occult-kranti.github.io/fact-duel/hisaab/#/q/hrf032 https://occult-kranti.github.io/fact-duel/hisaab/#/q/hrf024 | Y41: Indian Express — Kerala floods: On foreign aid, India follows policy set in tsunami aftermath (22 Aug 2018) | Z41: https://indianexpress.com/article/india/kerala-floods-on-foreign-aid-india-follows-policy-set-in-tsunami-aftermath-5318338/
A42: in-12th-fc-disaster-list-2005 | B42: 2005 | D42: 2005 | E42: Calamity funds widened (12th Finance Commission) | F42: relief | G42: Rahat Kosh (the relief fund) | H42: Centre | I42: IN | J42: India-wide (Centre) | K42: UPA | M42: Landslides, avalanches, cloudbursts and pest attacks added to the list calamity funds pay for | T42: Central releases to state calamity funds rose from ₹2,623 crore (2005-06) to ₹3,792 crore (2009-10), MHA data show. | V42: relief | W42: hrf009 | X42: https://occult-kranti.github.io/fact-duel/hisaab/#/q/hrf009 | Y42: Rajya Sabha Standing Committee on Home Affairs — 261st Report: Disaster Management (Aug 2026), paras 2.13.2–2.13.4 | Z42: https://bucketapi.rajyasabha.digital/public-bucket/uploads/committee/2026_08_21_committee_3339_976_6a881941b462a.pdf
A43: pb-rakshak-yojana-2005 | B43: 2005 | D43: 2005 | E43: Rakshak Yojana (girl child) | F43: distribution | G43: Seedha Khaate Mein (straight into the account) | H43: State | I43: PB | J43: Punjab | K43: INC | M43: A girl-child cash-transfer scheme | N43: 306 beneficiaries by March 2010 | T43: An IIPS–UNFPA review for the Planning Commission found paperwork and conditions blunted such schemes. | V43: distribution | W43: hdb102 | X43: https://occult-kranti.github.io/fact-duel/hisaab/#/q/hdb102 | Y43: Frontline — Off target (27 Jan 2012) | Z43: https://frontline.thehindu.com/other/article30164012.ece
A44: tn-tsunami-relief-2005 | B44: 2005-01 | D44: 2005 | E44: Tsunami relief package (Tamil Nadu) | F44: relief | G44: Rahat Kosh (the relief fund) | H44: State | I44: TN | J44: Tamil Nadu | K44: AIADMK | L44: J. Jayalalithaa (Chief Minister, Tamil Nadu, AIADMK) | M44: Clothes, rice, kerosene and ₹400 cash per family; boat repair aid | T44: The state sought ₹4,800 crore and 54,000 tonnes of rice from the Centre; Frontline noted relief grain leaking to the market. | V44: relief | W44: hrf105 | X44: https://occult-kranti.github.io/fact-duel/hisaab/#/q/hrf105 | Y44: Frontline — Rebuilding lives (28 Jan 2005) | Z44: https://frontline.thehindu.com/cover-story/article30203386.ece
A45: in-tsunami-relief-2005 | B45: 2005-02 | D45: 2005 | E45: Tsunami relief packages | F45: relief | G45: Rahat Kosh (the relief fund) | H45: Centre | I45: IN | J45: India-wide (Centre) | K45: UPA | L45: P. Chidambaram (Union Finance Minister, INC) | M45: Rajiv Gandhi Rehabilitation Package for Tamil Nadu, Kerala, Andhra, Puducherry and the Andamans | O45: ₹3,644 crore approved; ₹10,216 crore reconstruction plan | T45: Parliament’s PAC (2008) found diversions and lapses involving about ₹230 crore; only 250 of 10,000 Andaman houses were built by 2009. | V45: relief | W45: hrf007; hrf010 | X45: https://occult-kranti.github.io/fact-duel/hisaab/#/q/hrf007 https://occult-kranti.github.io/fact-duel/hisaab/#/q/hrf010 | Y45: indiabudget.gov.in — Budget Speech 2005-06, P. Chidambaram (28 Feb 2005), para 4 | Z45: https://www.indiabudget.gov.in/budget_archive/ub2005-06/bs/speecha.htm
A46: in-janani-suraksha-2005 | B46: 2005-04 | D46: 2005 | E46: Janani Suraksha Yojana | F46: distribution | G46: Seedha Khaate Mein (straight into the account) | H46: Centre | I46: IN | J46: India-wide (Centre) | K46: UPA | L46: Manmohan Singh (Prime Minister, INC) | M46: ₹1,400 to a rural mother in low-performing states for a facility birth (₹700 elsewhere) | T46: Institutional births rose from 38.7% (2005-06) to 90.6% (NFHS-6); a 2010 Lancet study linked payment to fewer perinatal deaths. | V46: distribution | W46: hdb007; hdb016 | X46: https://occult-kranti.github.io/fact-duel/hisaab/#/q/hdb007 https://occult-kranti.github.io/fact-duel/hisaab/#/q/hdb016 | Y46: National Health Mission — Janani Suraksha Yojana (accessed Sep 2026) | Z46: https://nhm.gov.in/index1.php?lang=1&level=3&sublinkid=841&lid=309
A47: mh-floods-relief-2005 | B47: 2005-07 | D47: 2005 | E47: July 2005 floods relief (Maharashtra) | F47: relief | G47: Rahat Kosh (the relief fund) | H47: State | I47: MH | J47: Maharashtra | K47: INC | L47: Vilasrao Deshmukh (Chief Minister, Maharashtra, INC) | M47: ₹500 crore state relief, with ₹500 crore more cleared by the Centre | N47: Over 1.87 lakh houses damaged; eight lakh families affected | T47: National highway repairs alone were put at over ₹4,100 crore. | V47: relief | W47: hrf108 | X47: https://occult-kranti.github.io/fact-duel/hisaab/#/q/hrf108 | Y47: Frontline — High water and hell (26 Aug 2005) | Z47: https://frontline.thehindu.com/cover-story/article30206092.ece
A48: pb-free-farm-power-restored-2005 | B48: 2005-11 | D48: 2005 | E48: Free farm power restored (Punjab) | F48: pre-election | G48: Chunav Se Pehle (before the vote) | H48: State | I48: PB | J48: Punjab | K48: INC | L48: Amarinder Singh (Chief Minister, Punjab, INC) | M48: Free electricity for farmers restored after a three-year break | P48: Punjab Assembly 2007 | Q48: 2007-02 | S48: SAD–BJP won 67 of 117 seats; Congress 44 | T48: The SAD–BJP won the February 2007 poll with 67 of 117 seats; the Congress fell from 62 to 44. | V48: distribution; pre-election | W48: hpe202 | X48: https://occult-kranti.github.io/fact-duel/hisaab/#/q/hpe202 | Y48: Outlook — 2007 Punjab Legislative Assembly Elections (26 Dec 2021) | Z48: https://www.outlookindia.com/opinion/india-news-2007-punjab-legislative-assembly-elections-news-305311
A49: gj-chiranjeevi-2005 | B49: 2005-12 | D49: 2005 | E49: Chiranjeevi Yojana | F49: distribution | G49: Seedha Khaate Mein (straight into the account) | H49: State | I49: GJ | J49: Gujarat | K49: BJP | M49: State pays private obstetricians to deliver poor women’s babies | N49: Over 6 lakh deliveries since 2007 | T49: A 2014 PLoS One study found it did not change the already rising private-sector share of births; caesareans under it were 6%. | V49: distribution | W49: hdb403 | X49: https://occult-kranti.github.io/fact-duel/hisaab/#/q/hdb403 | Y49: PLOS One — De Costa et al., The state-led large scale public private partnership ‘Chiranjeevi Program’ … in Gujarat (2014) | Z49: https://journals.plos.org/plosone/article?id=10.1371/journal.pone.0095704
A50: in-disaster-management-act-2005 | B50: 2005-12 | D50: 2005 | E50: Disaster Management Act, 2005 | F50: relief | G50: Rahat Kosh (the relief fund) | H50: Centre | I50: IN | J50: India-wide (Centre) | K50: UPA | M50: NDMA under the PM; provision for national and state disaster response and mitigation funds | T50: The mitigation fund came only after the 15th Finance Commission (2022); Parliament amended the Act in March 2025. | V50: relief | W50: hrf008 | X50: https://occult-kranti.github.io/fact-duel/hisaab/#/q/hrf008 | Y50: PRS Legislative Research — The Disaster Management Act, 2005 (Act No. 53 of 2005), text | Z50: https://prsindia.org/files/bills_acts/bills_parliament/2024/Disaster_Management_Act_2005.pdf
A51: tn-chennai-flood-relief-2005 | B51: 2005-12 | D51: 2005 | E51: Chennai flood relief camps (2005) | F51: relief | G51: Rahat Kosh (the relief fund) | H51: State | I51: TN | J51: Tamil Nadu | K51: AIADMK | M51: Relief token distribution at camps after the 2005 floods | T51: 42 died in a stampede at a K.K. Nagar camp; the Supreme Court said it was chiefly due to officers’ negligence. | V51: relief | W51: hrf107 | X51: https://occult-kranti.github.io/fact-duel/hisaab/#/q/hrf107 | Y51: Rediff (PTI) — TN govt responsible for December 2005 stampede: SC (27 Jan 2006) | Z51: https://www.rediff.com/news/report/stampede/20060127.htm
A52: br-cycle-yojana-2006 | B52: 2006 | D52: 2006 | E52: Mukhyamantri Cycle Yojana | F52: distribution | G52: Seedha Khaate Mein (straight into the account) | H52: State | I52: BR | J52: Bihar | K52: JD(U) | L52: Nitish Kumar (Chief Minister, Bihar, JD(U)) | M52: ₹2,000 to each Class 9 girl to buy a bicycle; opened to boys in 2009-10 | N52: 1.56 lakh girls (2007-08) to about 11.3 lakh students (2024-25) | T52: An IGC study (Mitra & Moene, 2017) found recipients 27.5% more likely to complete Class 10; the model was copied by other states. | V52: distribution | W52: hdb104; hdb118 | X52: https://occult-kranti.github.io/fact-duel/hisaab/#/q/hdb104 https://occult-kranti.github.io/fact-duel/hisaab/#/q/hdb118 | Y52: The Indian Express — Two decades ago, Nitish distributed cycles to girls in Class 9. Where are they now? (Nov 2025) | Z52: https://indianexpress.com/article/long-reads/two-decades-ago-nitish-distributed-cycles-to-girls-in-class-9-where-are-they-now-10360460/
A53: kl-tsunami-rehabilitation-2006 | B53: 2006 | D53: 2006 | E53: Tsunami Rehabilitation Programme (Kerala) | F53: relief | G53: Rahat Kosh (the relief fund) | H53: State | I53: KL | J53: Kerala | K53: LDF | M53: Centrally approved rehabilitation programme; ₹284.08 crore moved from coastal protection to housing | O53: ₹1,441.75 crore programme | T53: CAG (2013): 8,549 of 11,000 houses built by July 2012; 72 of 228 chosen villages were not on the coast. | V53: relief | W53: hrf106 | X53: https://occult-kranti.github.io/fact-duel/hisaab/#/q/hrf106 | Y53: The New Indian Express — 'Grave lapses in Tsunami Rehabilitation Programme' (20 Mar 2013) | Z53: https://www.newindianexpress.com/states/kerala/2013/Mar/20/grave-lapses-in-tsunami-rehabilitation-programme-460171.html
A54: in-nrega-2006 | B54: 2006-02 | D54: 2006 | E54: NREGA / MGNREGA rural jobs guarantee | F54: distribution | G54: Seedha Khaate Mein (straight into the account) | H54: Centre | I54: IN | J54: India-wide (Centre) | K54: UPA | L54: Manmohan Singh (Prime Minister, INC); Raghuvansh Prasad Singh (Union Rural Development Minister, RJD) | M54: 100 days of wage work a year guaranteed to every rural household | N54: 3.51 crore households in 2008-09; 4,872 crore person-days by 2025 | O54: ₹86,000 crore (2025-26); about ₹11.7 lakh crore since 2005 | T54: Only 4% of households got 100 days in 2024-25 (PRS). Replaced by the VB-G RAM G Act from 1 July 2026. | V54: distribution; pre-election | W54: hdb009; hdb008; hsc040; hdb011; hdb014; hpe012; hsc038; hsc039; hsc041; hdb041; hdb328 | X54: https://occult-kranti.github.io/fact-duel/hisaab/#/q/hdb009 https://occult-kranti.github.io/fact-duel/hisaab/#/q/hdb008 https://occult-kranti.github.io/fact-duel/hisaab/#/q/hsc040 https://occult-kranti.github.io/fact-duel/hisaab/#/q/hdb011 https://occult-kranti.github.io/fact-duel/hisaab/#/q/hdb014 https://occult-kranti.github.io/fact-duel/hisaab/#/q/hpe012 https://occult-kranti.github.io/fact-duel/hisaab/#/q/hsc038 https://occult-kranti.github.io/fact-duel/hisaab/#/q/hsc039 https://occult-kranti.github.io/fact-duel/hisaab/#/q/hsc041 https://occult-kranti.github.io/fact-duel/hisaab/#/q/hdb041 https://occult-kranti.github.io/fact-duel/hisaab/#/q/hdb328 | Y54: The Hindu — NREGS transforms Bandlapalli, where it was launched in 2006 (1 Feb 2021) | Z54: https://www.thehindu.com/news/national/andhra-pradesh/nregs-transforms-bandlapalli-where-it-was-launched-in-2006/article33721578.ece
A55: up-unemployment-allowance-2006 | B55: 2006-02 | D55: 2006 | E55: Unemployment allowance (UP, 2006) | F55: distribution | G55: Seedha Khaate Mein (straight into the account) | H55: State | I55: UP | J55: Uttar Pradesh | K55: SP | L55: Mulayam Singh Yadav (Chief Minister, Uttar Pradesh, SP) | M55: ₹500 a month to registered unemployed graduates | O55: ₹250 crore a year (estimate) | T55: Registrations surged; the BSP government scrapped it and the SP revived it at ₹1,000 in 2012. | V55: distribution | W55: hdb103 | X55: https://occult-kranti.github.io/fact-duel/hisaab/#/q/hdb103 | Y55: Hindustan Times — Unemployment dole (26 Mar 2006) | Z55: https://www.hindustantimes.com/india/unemployment-dole/story-4nNvKmDAYGRN0MfOx1iDKP.html
A56: tn-co-op-loan-waiver-2006 | B56: 2006-05 | D56: 2006 | E56: Co-operative loan waiver (Tamil Nadu, 2006) | F56: distribution | G56: Seedha Khaate Mein (straight into the account) | H56: State | I56: TN | J56: Tamil Nadu | K56: DMK | L56: M. Karunanidhi (Chief Minister, Tamil Nadu, DMK) | M56: Farmers’ co-operative loans waived; rice at ₹2 a kg; two eggs a week in the noon meal | O56: ₹6,866 crore (waiver) | T56: Signed on oath day as the DMK manifesto promised; the DMK-led front had won 163 of 234. | V56: distribution; pre-election | W56: hpe104 | X56: https://occult-kranti.github.io/fact-duel/hisaab/#/q/hpe104 | Y56: Frontline — Promises to keep (2 Jun 2006) | Z56: https://frontline.thehindu.com/cover-story/article30209583.ece
A57: tn-free-colour-tv-2006 | B57: 2006-09 | D57: 2006 | E57: Free colour TV scheme | F57: distribution | G57: Seedha Khaate Mein (straight into the account) | H57: State | I57: TN | J57: Tamil Nadu | K57: DMK | L57: M. Karunanidhi (Chief Minister, Tamil Nadu, DMK) | M57: A free colour TV for every family without one | N57: 14.6 lakh sets in the first ten months | O57: ₹530 crore a year (DMK’s 2006 estimate) | T57: The EC halted handouts in March 2011; the AIADMK won 203 of 234 with allies and scrapped it. The SC’s 2013 ruling on freebies arose from it. | V57: distribution; pre-election | W57: hdb205; hdb206; hdb213; hpe103; hpe108; hpe015 | X57: https://occult-kranti.github.io/fact-duel/hisaab/#/q/hdb205 https://occult-kranti.github.io/fact-duel/hisaab/#/q/hdb206 https://occult-kranti.github.io/fact-duel/hisaab/#/q/hdb213 https://occult-kranti.github.io/fact-duel/hisaab/#/q/hpe103 https://occult-kranti.github.io/fact-duel/hisaab/#/q/hpe108 https://occult-kranti.github.io/fact-duel/hisaab/#/q/hpe015 | Y57: Times of India — 'Free TV' soap opera is a hit in TN (Sep 2006) | Z57: https://timesofindia.indiatimes.com/india/free-tv-soap-opera-is-a-hit-in-tn/articleshow/1996396.cms
A58: as-floods-majuli-2007 | B58: 2007 | D58: 2007 | E58: Assam floods: Majuli package | F58: relief | G58: Rahat Kosh (the relief fund) | H58: State | I58: AS | J58: Assam | K58: INC | L58: Tarun Gogoi (Chief Minister, Assam, INC) | M58: ₹100 crore development package for Majuli after the Matmora embankment breach | N58: Over 1.35 lakh islanders displaced | T58: Frontline found most embankments over 40 years old; the state was banking on a ₹1,600 crore ADB-funded flood project. | V58: relief | W58: hrf203 | X58: https://occult-kranti.github.io/fact-duel/hisaab/#/q/hrf203 | Y58: Frontline — Torrent of sorrow (19 Oct 2007) | Z58: https://frontline.thehindu.com/other/article30193144.ece
A59: mp-ladli-laxmi-2007 | B59: 2007-05 | D59: 2007 | E59: Ladli Laxmi Yojana | F59: distribution | G59: Seedha Khaate Mein (straight into the account) | H59: State | I59: MP | J59: Madhya Pradesh | K59: BJP | L59: Shivraj Singh Chouhan (Chief Minister, Madhya Pradesh, BJP) | M59: Savings certificates of ₹6,000 a year for five years; staged payments and over ₹1 lakh at 21 | N59: Over 23 lakh girls by 2016; 3.45 lakh registered in 2020-21 | O59: ₹1,363.62 crore (2020-21) | T59: Registrations and spending peaked in 2020-21; each registration commits the state to about ₹1 lakh at 21. | V59: distribution | W59: hdb207; hdb244 | X59: https://occult-kranti.github.io/fact-duel/hisaab/#/q/hdb207 https://occult-kranti.github.io/fact-duel/hisaab/#/q/hdb244 | Y59: OneIndia (UNI) — Ladli Lakshmi Yojana in MP (2 May 2007) | Z59: https://www.oneindia.com/2007/05/02/ladli-lakshmi-yojana-in-mp-1178120286.html
A60: pb-atta-dal-2007 | B60: 2007-08 | D60: 2007 | E60: Atta-dal scheme | F60: distribution | G60: Seedha Khaate Mein (straight into the account) | H60: State | I60: PB | J60: Punjab | K60: SAD | L60: Parkash Singh Badal (Chief Minister, Punjab, SAD) | M60: Wheat at ₹4 a kg and chana dal at ₹20 a kg for poor families | T60: Folded into the NFSA; wheat free since Covid. About 23 lakh NFSA beneficiaries were weeded out in two years (Tribune). | V60: distribution | W60: hdb105 | X60: https://occult-kranti.github.io/fact-duel/hisaab/#/q/hdb105 | Y60: The Tribune — Mann govt to provide free ration kits to 40L families ahead of poll (24 Feb 2026) | Z60: https://www.tribuneindia.com/news/top-headlines/mann-govt-to-provide-free-ration-kits-to-40l-families-ahead-of-poll/
A61: in-ignoaps-2007 | B61: 2007-11 | D61: 2007 | E61: Old-age pension (IGNOAPS / NSAP) | F61: distribution | G61: Seedha Khaate Mein (straight into the account) | H61: Centre | I61: IN | J61: India-wide (Centre) | K61: UPA | M61: Central pension for all BPL persons aged 65+ (later 60+), ₹200 a month since 2012 | N61: 146 lakh pensioners in 2008-09 | O61: ₹9,652 crore for NSAP (2025-26) | T61: A 2026 ministry study found inflation had cut the ₹200’s real value by about 45%; the Centre says no rise is proposed. | V61: distribution; relief | W61: hdb010; hdb043; hdb033 | X61: https://occult-kranti.github.io/fact-duel/hisaab/#/q/hdb010 https://occult-kranti.github.io/fact-duel/hisaab/#/q/hdb043 https://occult-kranti.github.io/fact-duel/hisaab/#/q/hdb033 | Y61: indiabudget.gov.in — Interim Budget Speech 2009-10, Pranab Mukherjee (16 Feb 2009) | Z61: https://www.indiabudget.gov.in/budget_archive/ub2009-10(I)/bs/speecha.htm
A62: dl-ladli-2008 | B62: 2008 | D62: 2008 | E62: Ladli scheme (Delhi) | F62: pre-election | G62: Chunav Se Pehle (before the vote) | H62: State | I62: DL | J62: Delhi | K62: INC | L62: Sheila Dikshit (Chief Minister, Delhi, INC) | M62: Instalments through a girl’s schooling plus up to ₹1 lakh at 18 | N62: 8.84 lakh active beneficiaries (Dec 2022) | P62: Delhi Assembly 2008 | Q62: 2008-11 | S62: Congress won 43 of 70; BJP 23 | T62: CAG (2025): ₹618.38 crore unclaimed, 55% of active beneficiaries unpaid, 16,546 duplicates. To be replaced by Lakhpati Bitiya from April 2026. | V62: distribution; pre-election | W62: hpe151; hdb128 | X62: https://occult-kranti.github.io/fact-duel/hisaab/#/q/hpe151 https://occult-kranti.github.io/fact-duel/hisaab/#/q/hdb128 | Y62: The New Indian Express — 'Duplicate registrations': CAG exposes Rs 220 crore irregularities in Ladli scheme (27 Feb 2025) | Z62: https://www.newindianexpress.com/cities/delhi/2025/Feb/27/ladli-scheme-audit-finds-rs-61838-crore-unclaimed-reveals-massive-irregularities
A63: rj-bhamashah-2008 | B63: 2008 | D63: 2008 | E63: Bhamashah, first version | F63: pre-election | G63: Chunav Se Pehle (before the vote) | H63: State | I63: RJ | J63: Rajasthan | K63: BJP | L63: Vasundhara Raje (Chief Minister, Rajasthan, BJP) | M63: Bank accounts for women heads of families, with transfers into them | N63: 26 lakh accounts; 10 lakh credited | O63: About ₹160 crore transferred | P63: Rajasthan Assembly 2008 | Q63: 2008-12 | S63: Congress won 96 of 200; BJP 78 | T63: The Congress won 96 of 200 in December 2008 and dropped the scheme; it returned in 2014. | V63: distribution; pre-election | W63: hpe106 | X63: https://occult-kranti.github.io/fact-duel/hisaab/#/q/hpe106 | Y63: The Hindu — Vasundhara to re-launch scheme to empower women (15 Aug 2014) | Z63: https://www.thehindu.com/news/national/other-states/vasundhara-to-relaunch-scheme-to-empower-women/article6319335.ece
A64: ct-rice-3-a-kg-2008 | B64: 2008-01 | D64: 2008 | E64: Rice at ₹3 a kg and salt at 25 paise (Chhattisgarh) | F64: pre-election | G64: Chunav Se Pehle (before the vote) | H64: State | I64: CT | J64: Chhattisgarh | K64: BJP | L64: Raman Singh (Chief Minister, Chhattisgarh, BJP) | M64: 35 kg of rice a month at ₹3 a kg for BPL families, then salt at 25 paise a kg | N64: Nearly 34 lakh BPL families | O64: ₹837 crore (costed at launch) | P64: Chhattisgarh Assembly 2008 | Q64: 2008-11 | R64: 303 | S64: BJP retained power with 50 of 90 seats; Congress 38 | T64: The BJP kept power in November 2008 with 50 of 90 seats; by 2013 Frontline found even adversaries crediting the cheap-rice scheme. | V64: distribution; pre-election | W64: hdb208; hpe105 | X64: https://occult-kranti.github.io/fact-duel/hisaab/#/q/hdb208 https://occult-kranti.github.io/fact-duel/hisaab/#/q/hpe105 | Y64: Times of India — Chhattisgarh poor to get rice at Rs 3/kg (17 Jan 2008) | Z64: https://timesofindia.indiatimes.com/india/chhattisgarh-poor-to-get-rice-at-rs-3/kg/articleshow/2706349.cms
A65: od-mo-kudia-2008 | B65: 2008-01 | D65: 2008 | E65: Mo Kudia (My Hut) | F65: distribution | G65: Seedha Khaate Mein (straight into the account) | H65: State | I65: OD | J65: Odisha | K65: BJD | L65: Naveen Patnaik (Chief Minister, Odisha, BJD) | M65: State-funded houses (₹25,000 each at first) for poor families left off the BPL list | N65: About 15 lakh households targeted over five years (2014) | T65: Folded into Biju Pucca Ghar in September 2014. | V65: distribution | W65: hdb336 | X65: https://occult-kranti.github.io/fact-duel/hisaab/#/q/hdb336 | Y65: The Times of India — Government renames Mo Kudia scheme (12 Sep 2014) | Z65: https://timesofindia.indiatimes.com/city/bhubaneswar/Government-renames-Mo-Kudia-scheme/articleshow/42329187.cms
A66: in-farm-debt-waiver-2008 | B66: 2008-02 | D66: 2008 | E66: Farm debt waiver and relief | F66: pre-election | G66: Chunav Se Pehle (before the vote) | H66: Centre | I66: IN | J66: India-wide (Centre) | K66: UPA | L66: P. Chidambaram (Union Finance Minister, INC) | M66: Overdue loans of small and marginal farmers waived; 25% one-time settlement for others | N66: 3.6 crore farmers (early reports) | O66: ₹60,000 crore estimated; ₹65,300 crore reported in 2009 | P66: Lok Sabha 2009 | Q66: 2009-04 | R66: 412 | S66: INC 206 seats; the Congress-led UPA returned with 262 | T66: CAG (2013): 8.5% of test-checked beneficiaries ineligible and 13.46% of eligible left out. The UPA returned in 2009 (Congress 206). | V66: distribution; pre-election | W66: hdb012; hdb013; hdb021; hpe016 | X66: https://occult-kranti.github.io/fact-duel/hisaab/#/q/hdb012 https://occult-kranti.github.io/fact-duel/hisaab/#/q/hdb013 https://occult-kranti.github.io/fact-duel/hisaab/#/q/hdb021 https://occult-kranti.github.io/fact-duel/hisaab/#/q/hpe016 | Y66: indiabudget.gov.in — Budget Speech 2008-09, P. Chidambaram (29 Feb 2008) | Z66: https://www.indiabudget.gov.in/budget_archive/ub2008-09/bs/speecha.htm
A67: in-income-tax-limit-2008 | B67: 2008-02 | D67: 2008 | E67: Income-tax exemption limit raised | F67: pre-election | G67: Chunav Se Pehle (before the vote) | H67: Centre | I67: IN | J67: India-wide (Centre) | K67: UPA | L67: P. Chidambaram (Union Finance Minister, INC) | M67: Basic exemption raised from ₹1.1 lakh to ₹1.5 lakh; every assessee gained at least ₹4,000 | P67: Lok Sabha 2009 | Q67: 2009-04 | R67: 412 | S67: INC won 206 seats, its best since 1991; the Congress-led UPA returned to power | T67: Polling began 412 days later; the Congress won 206 seats. The cited sources make no causal claim. | V67: pre-election | W67: hpe007 | X67: https://occult-kranti.github.io/fact-duel/hisaab/#/q/hpe007 | Y67: indiabudget.gov.in — Budget Speech 2008-09, P. Chidambaram (29 Feb 2008) | Z67: https://www.indiabudget.gov.in/budget_archive/ub2008-09/bs/speecha.htm
A68: in-rsby-2008 | B68: 2008-02 | D68: 2008 | E68: Rashtriya Swasthya Bima Yojana | F68: pre-election | G68: Chunav Se Pehle (before the vote) | H68: Centre | I68: IN | J68: India-wide (Centre) | K68: UPA | L68: P. Chidambaram (Union Finance Minister, INC) | M68: ₹30,000 hospital cover for BPL families of unorganised-sector workers | N68: Over 46 lakh BPL families by July 2009 | O68: ₹205 crore central premium share (2008-09) | P68: Lok Sabha 2009 | Q68: 2009-04 | R68: 412 | S68: INC won 206 seats, its best since 1991; the Congress-led UPA returned to power | T68: Its 2009-10 allocation rose 40% to ₹350 crore; the UPA was re-elected in May 2009. | V68: distribution; pre-election | W68: hpe008 | X68: https://occult-kranti.github.io/fact-duel/hisaab/#/q/hpe008 | Y68: indiabudget.gov.in — Budget Speech 2008-09, P. Chidambaram (29 Feb 2008) | Z68: https://www.indiabudget.gov.in/budget_archive/ub2008-09/bs/speecha.htm
A69: ap-rice-2-a-kg-2008 | B69: 2008-04 | D69: 2008 | E69: Rice at ₹2 a kg (Andhra Pradesh) | F69: pre-election | G69: Chunav Se Pehle (before the vote) | H69: State | I69: AP | J69: Andhra Pradesh | K69: INC | L69: Y.S. Rajasekhara Reddy (Chief Minister, Andhra Pradesh, INC) | M69: Rice at ₹2 a kg for BPL families, reviving a scheme pioneered by N.T. Rama Rao | N69: About 1.87 crore BPL families (state estimate) | P69: Andhra Pradesh Assembly 2009 | Q69: 2009-04 | R69: 372 | S69: Congress retained power with 156 of 294 seats; TDP 92 | T69: The Congress was re-elected in April 2009 with 156 of 294 seats; the TDP won 92. | V69: distribution; pre-election | W69: hdb209 | X69: https://occult-kranti.github.io/fact-duel/hisaab/#/q/hdb209 | Y69: Times of India — Poll sop: Rice at Rs 2/kg in Andhra (10 Apr 2008) | Z69: https://timesofindia.indiatimes.com/india/poll-sop-rice-at-rs-2/kg-in-andhra/articleshow/2939135.cms
A70: br-kosi-floods-2008 | B70: 2008-08 | D70: 2008 | E70: Kosi floods central aid | F70: relief | G70: Rahat Kosh (the relief fund) | H70: Centre | I70: BR | J70: Bihar | K70: UPA | L70: Manmohan Singh (Prime Minister, INC) | M70: ₹1,000 crore and 1.25 lakh tonnes of grain; floods declared a ‘national disaster’ | N70: Nearly 20 lakh people displaced | T70: The Centre met Bihar’s ₹1,000 crore request in full and exceeded its grain request. | V70: relief | W70: hrf011 | X70: https://occult-kranti.github.io/fact-duel/hisaab/#/q/hrf011 | Y70: Economic Times — PM sanctions Rs 1,000 crore, declares Bihar flood national disaster (29 Aug 2008) | Z70: https://economictimes.indiatimes.com/news/politics-and-nation/pm-sanctions-rs-1000-crore-declares-bihar-flood-national-disaster/articleshow/3419064.cms
A71: in-sixth-pay-commission-2008 | B71: 2008-08 | D71: 2008 | E71: Sixth Pay Commission award | F71: pre-election | G71: Chunav Se Pehle (before the vote) | H71: Centre | I71: IN | J71: India-wide (Centre) | K71: UPA | L71: Pranab Mukherjee (Union Finance Minister, INC) | M71: Pay revised from 1 January 2006; minimum pay ₹7,000 a month | N71: Over 45 lakh employees and 38 lakh pensioners | P71: Lok Sabha 2009 | Q71: 2009-04 | S71: INC won 206 seats, its best since 1991; the Congress-led UPA returned to power | T71: The July 2009 budget said non-plan spending rose mainly on the pay award; the UPA had returned with the Congress at 206. | V71: pre-election | W71: hpe009 | X71: https://occult-kranti.github.io/fact-duel/hisaab/#/q/hpe009 | Y71: indiabudget.gov.in — Interim Budget 2009-10 speech, Pranab Mukherjee (16 Feb 2009) | Z71: https://www.indiabudget.gov.in/budget_archive/ub2009-10(I)/bs/speecha.htm
A72: od-rice-2-a-kg-2008 | B72: 2008-08 | D72: 2008 | E72: Rice at ₹2 a kg (Odisha) | F72: pre-election | G72: Chunav Se Pehle (before the vote) | H72: State | I72: OD | J72: Odisha | K72: BJD | L72: Naveen Patnaik (Chief Minister, Odisha, BJD) | M72: Rice at ₹2 a kg for poor families, the state paying above the central subsidy (it was ₹4.75 in 2001) | P72: Odisha Assembly 2009 | Q72: 2009-04 | R72: 258 | S72: BJD won 103 of 147 seats | T72: The BJD returned with 103 of 147 seats in 2009. No study cited links the result to the scheme. | V72: distribution; pre-election | W72: hdb313; hdb311 | X72: https://occult-kranti.github.io/fact-duel/hisaab/#/q/hdb313 https://occult-kranti.github.io/fact-duel/hisaab/#/q/hdb311 | Y72: The Indian Express — Naveen is Orissa CM for record fourth time (22 May 2014) | Z72: https://indianexpress.com/article/political-pulse/naveen-is-orissa-cm-for-record-fourth-time/
A73: tn-rice-1-a-kg-2008 | B73: 2008-09 | D73: 2008 | E73: Rice at ₹1 a kg (Tamil Nadu) | F73: pre-election | G73: Chunav Se Pehle (before the vote) | H73: State | I73: TN | J73: Tamil Nadu | K73: DMK | L73: M. Karunanidhi (Chief Minister, Tamil Nadu, DMK) | M73: Up to 20 kg of PDS rice a month at ₹1 a kg | N73: 1.86 crore ration-card families | O73: About ₹400 crore a year extra | P73: Lok Sabha 2009 (Tamil Nadu) | Q73: 2009-05 | R73: 256 | S73: DMK-led alliance won 27 of 39 seats; AIADMK-led front 12 | T73: The DMK-led alliance won 27 of Tamil Nadu’s 39 Lok Sabha seats in 2009. | V73: distribution; pre-election | W73: hdb210 | X73: https://occult-kranti.github.io/fact-duel/hisaab/#/q/hdb210 | Y73: Times of India — Rice at Re 1 per kg in TN (31 Aug 2008) | Z73: https://timesofindia.indiatimes.com/city/chennai/rice-at-re-1-per-kg-in-tn-from-sept-5/articleshow/3426920.cms
A74: in-excise-stimulus-2008 | B74: 2008-12 | D74: 2008 | E74: Excise cuts and stimulus | F74: pre-election | G74: Chunav Se Pehle (before the vote) | H74: Centre | I74: IN | J74: India-wide (Centre) | K74: UPA | L74: Pranab Mukherjee (Union Finance Minister, INC) | M74: CENVAT on non-petroleum goods cut by 6 points in all (Dec 2008–Feb 2009) | O74: Stimulus of ₹1,86,000 crore; deficit 2.7% to 6.2% of GDP | P74: Lok Sabha 2009 | Q74: 2009-04 | R74: 51 | S74: INC won 206 seats, its best since 1991; the Congress-led UPA returned to power | T74: The last cut came 51 days before polling; the UPA returned with the Congress at 206 seats. | V74: pre-election | W74: hpe011 | X74: https://occult-kranti.github.io/fact-duel/hisaab/#/q/hpe011 | Y74: indiabudget.gov.in — Budget Speech 2009-10, Pranab Mukherjee (6 Jul 2009) | Z74: https://www.indiabudget.gov.in/budget_archive/ub2009-10/bs/speecha.htm
A75: gj-garib-kalyan-melas-2009 | B75: 2009 | D75: 2009 | E75: Garib Kalyan Melas | F75: distribution | G75: Seedha Khaate Mein (straight into the account) | H75: State | I75: GJ | J75: Gujarat | K75: BJP | L75: Narendra Modi (Chief Minister, Gujarat, BJP) | M75: Public events where scheme benefits and tool kits are handed to poor families | N75: 1.66 crore people via 1,600+ melas (state figure, 2024) | O75: ₹36,800 crore handed out in all (state figure, 2024) | T75: The 14th round in Sept 2024 was to hand out ₹4,568 crore, CM Bhupendra Patel said. | V75: distribution | W75: hdb404 | X75: https://occult-kranti.github.io/fact-duel/hisaab/#/q/hdb404 | Y75: The Indian Express — Gujarat CM Bhupendra Patel launches 14th Garib Kalyan Mela, says Rs 4568 crore to be distributed among poor (27 Sep 2024) | Z75: https://indianexpress.com/article/cities/ahmedabad/gujarat-cm-bhupendra-patel-launches-14th-garib-kalyan-mela-9591151/
A76: ka-aasare-flood-houses-2009 | B76: 2009 | D76: 2009 | E76: Aasare flood houses | F76: relief | G76: Rahat Kosh (the relief fund) | H76: State | I76: KA | J76: Karnataka | K76: BJP | L76: B.S. Yeddyurappa (Chief Minister, Karnataka, BJP) | M76: 1,00,000 houses at ₹1 lakh each for north Karnataka flood victims | T76: In Raichur, 11,123 of 12,241 houses were built by 2013, but many stood empty for want of water and power. | V76: relief | W76: hrf109 | X76: https://occult-kranti.github.io/fact-duel/hisaab/#/q/hrf109 | Y76: Frontline — After the deluge (6 Nov 2009) | Z76: https://frontline.thehindu.com/the-nation/article30188800.ece
A77: mh-slum-cutoff-2009 | B77: 2009 | D77: 2009 | E77: Slum regularisation cut-off moved to 2000 | F77: pre-election | G77: Chunav Se Pehle (before the vote) | H77: State | I77: MH | J77: Maharashtra | K77: INC | L77: Ashok Chavan (Chief Minister, Maharashtra, INC) | M77: Mumbai slum encroachments up to 2000 made eligible for regularisation | N77: About 75 lakh slum-dwellers in Mumbai | P77: Maharashtra Assembly 2009 | Q77: 2009-10 | S77: Congress 82, NCP 62 of 288: the Congress–NCP alliance kept power | T77: The order awaited the Supreme Court as the High Court had barred extensions; the Congress–NCP kept power. | V77: pre-election | W77: hpe203 | X77: https://occult-kranti.github.io/fact-duel/hisaab/#/q/hpe203 | Y77: Frontline — Promises to Mumbai (23 Oct 2009) | Z77: https://frontline.thehindu.com/politics/article30188745.ece
A78: up-bundelkhand-package-2009 | B78: 2009 | D78: 2009 | E78: Bundelkhand drought package | F78: relief | G78: Rahat Kosh (the relief fund) | H78: Centre | I78: UP | J78: Uttar Pradesh | K78: UPA | M78: Central drought package for Bundelkhand districts of UP and MP | O78: ₹7,266 crore (2009–12) | T78: UP had spent ₹280.99 crore of ₹860.97 crore released by Nov 2011; the Centre extended it with ₹4,400 crore for 2012–17. | V78: relief | W78: hrf204 | X78: https://occult-kranti.github.io/fact-duel/hisaab/#/q/hrf204 | Y78: The Hindu — Whither Bundelkhand package? (12 Feb 2012) | Z78: https://www.thehindu.com/news/national/whither-bundelkhand-package/article2883401.ece
A79: wb-subsidised-rice-2009 | B79: 2009 | D79: 2009 | E79: Subsidised rice (West Bengal, 2009) | F79: distribution | G79: Seedha Khaate Mein (straight into the account) | H79: State | I79: WB | J79: West Bengal | K79: CPI(M) | M79: Subsidised rice for poor families | N79: 2.64 crore BPL people | T79: The Left lost power in 2011; the TMC widened coverage by 20% to 3.2 crore. | V79: distribution | W79: hdb300 | X79: https://occult-kranti.github.io/fact-duel/hisaab/#/q/hdb300 | Y79: The Indian Express — In Jangalmahal village that once went hungry, 'parivartan' takes the form of affordable rice (28 Mar 2016) | Z79: https://indianexpress.com/article/india/india-news-india/west-bengal-assembly-elections-2016-in-jangalmahal-village-that-once-went-hungry-parivartan-takes-the-form-of-affordable-rice/
A80: up-balika-ashirvad-2009 | B80: 2009-01 | D80: 2009 | E80: Mahamaya Garib Balika Ashirvad Yojana | F80: pre-election | G80: Chunav Se Pehle (before the vote) | H80: State | I80: UP | J80: Uttar Pradesh | K80: BSP | L80: Mayawati (Chief Minister, Uttar Pradesh, BSP) | M80: ₹22,000 savings certificate for each girl born to a BPL family, growing to ₹1 lakh at 18 | O80: About ₹2,000 crore with a sister scheme | P80: Lok Sabha 2009 (Uttar Pradesh) | Q80: 2009-04 | R80: 91 | S80: BSP won 20 of UP’s 80 seats; SP 23, Congress 21, BJP 10 | T80: The BSP won 20 of UP’s 80 Lok Sabha seats in 2009, behind the SP’s 23. | V80: distribution; pre-election | W80: hdb106 | X80: https://occult-kranti.github.io/fact-duel/hisaab/#/q/hdb106 | Y80: The Indian Express — Announced on Maya’s birthday, schemes executed in 20 days (5 Feb 2009) | Z80: https://indianexpress.com/article/cities/lucknow/announced-on-maya-s-birthday-schemes-execut/
A81: in-rail-fare-cut-2009 | B81: 2009-02 | D81: 2009 | E81: Interim Railway Budget fare cut | F81: pre-election | G81: Chunav Se Pehle (before the vote) | H81: Centre | I81: IN | J81: India-wide (Centre) | K81: UPA | L81: Lalu Prasad (Union Railway Minister, RJD) | M81: 2% cut in passenger fares across the board | O81: About ₹700 crore of passenger earnings | P81: Lok Sabha 2009 | Q81: 2009-04 | R81: 62 | S81: INC won 206 seats, its best since 1991; the Congress-led UPA returned to power | T81: Polling began 62 days later; the UPA returned to power. | V81: pre-election | W81: hpe010 | X81: https://occult-kranti.github.io/fact-duel/hisaab/#/q/hpe010 | Y81: The Indian Express — 2% fare cut is the only Lalu stimulus (13 Feb 2009) | Z81: https://indianexpress.com/article/india/india-others/2-fare-cut-is-the-only-lalu-stimulus/
A82: hr-old-age-allowance-2009 | B82: 2009-03 | D82: 2009 | E82: Old Age Samman Allowance raised to ₹500–700 | F82: pre-election | G82: Chunav Se Pehle (before the vote) | H82: State | I82: HR | J82: Haryana | K82: INC | L82: Bhupinder Singh Hooda (Chief Minister, Haryana, INC) | M82: Old-age allowance raised from ₹300 to ₹500–700 a month | P82: Haryana Assembly 2009 | Q82: 2009-10 | R82: 226 | S82: Congress won 40 of 90 seats and formed the government; INLD 31 | T82: The Congress won 40 of 90 seats and formed the government; the allowance rose to ₹1,000 from January 2014. | V82: distribution; pre-election | W82: hdb107 | X82: https://occult-kranti.github.io/fact-duel/hisaab/#/q/hdb107 | Y82: Government of Haryana, Social Justice & Empowerment — Old Age Samman Allowance Scheme (rate history, updated Jul 2026) | Z82: https://socialjusticehry.gov.in/old-age-samman-allowance-scheme/
A83: wb-cyclone-aila-2009 | B83: 2009-05 | D83: 2009 | E83: Cyclone Aila relief | F83: relief | G83: Rahat Kosh (the relief fund) | H83: State | I83: WB | J83: West Bengal | K83: CPI(M) | L83: Buddhadeb Bhattacharjee (Chief Minister, West Bengal, CPI(M)) | M83: ₹40 crore, free rice and dal, tarpaulins | N83: Over 40 lakh people affected | T83: A ₹5,032 crore embankment project followed; three years on, not a kilometre was complete (DTE). | V83: relief | W83: hrf205 | X83: https://occult-kranti.github.io/fact-duel/hisaab/#/q/hrf205 | Y83: Frontline — Aila's wrath (19 Jun 2009) | Z83: https://frontline.thehindu.com/the-nation/article30187387.ece
A84: ka-andhra-floods-2009 | B84: 2009-10 | D84: 2009 | E84: Karnataka–Andhra floods central aid | F84: relief | G84: Rahat Kosh (the relief fund) | H84: Centre | I84: KA | J84: Karnataka | K84: UPA | L84: Manmohan Singh (Prime Minister, INC) | M84: ₹1,000 crore interim relief each for Karnataka and Andhra Pradesh; ₹1 lakh per death | T84: ₹2,000 crore in interim aid, with more promised after central teams assessed the memoranda. | V84: relief | W84: hrf012 | X84: https://occult-kranti.github.io/fact-duel/hisaab/#/q/hrf012 | Y84: The Hindu (IANS) — Manmohan winds up survey; announces Rs. 2,000 cr. relief (10 Oct 2009) | Z84: https://www.thehindu.com/news/national/Manmohan-winds-up-survey-announces-Rs.-2000-cr.-relief/article16885881.ece
A85: in-sdrf-ndrf-2010 | B85: 2010 | D85: 2010 | E85: SDRF and NDRF (13th Finance Commission) | F85: relief | G85: Rahat Kosh (the relief fund) | H85: Centre | I85: IN | J85: India-wide (Centre) | K85: UPA | M85: Old calamity funds folded into State and National Disaster Response Funds; Centre pays 75% (90% special-category) | O85: ₹33,581 crore allocation (2010–15) | T85: NDRF releases peaked at ₹18,531 crore in 2019-20. CAG: only about ₹5,356 crore of ₹11,474 crore of 2024-25 NDRF aid reached states. | V85: relief | W85: hrf013; hrf027; hrf039 | X85: https://occult-kranti.github.io/fact-duel/hisaab/#/q/hrf013 https://occult-kranti.github.io/fact-duel/hisaab/#/q/hrf027 https://occult-kranti.github.io/fact-duel/hisaab/#/q/hrf039 | Y85: Rajya Sabha Standing Committee on Home Affairs — 261st Report: Disaster Management (Aug 2026), para 2.13.4 | Z85: https://bucketapi.rajyasabha.digital/public-bucket/uploads/committee/2026_08_21_committee_3339_976_6a881941b462a.pdf
A86: br-gujarat-kosi-aid-returned-2010 | B86: 2010-06 | D86: 2010 | E86: Gujarat’s Kosi aid returned | F86: relief | G86: Rahat Kosh (the relief fund) | H86: State | I86: BR | J86: Bihar | K86: JD(U) | L86: Nitish Kumar (Chief Minister, Bihar, JD(U)) | M86: ₹5 crore from the Gujarat government for 2008 Kosi flood victims, returned by Bihar | T86: Nitish Kumar returned the cheque after newspaper ads; Modi called the return ‘arrogant’ while campaigning in Bihar in 2015. | V86: relief | W86: hrf110 | X86: https://occult-kranti.github.io/fact-duel/hisaab/#/q/hrf110 | Y86: Rediff — When Nitish cancelled the Modi dinner (book excerpt, 28 Feb 2014) | Z86: https://www.rediff.com/news/slide-show/slide-show-1-when-nitish-cancelled-the-modi-dinner/20140228.htm
A87: in-igmsy-2010 | B87: 2010-10 | D87: 2010 | E87: Indira Gandhi Matritva Sahyog Yojana | F87: distribution | G87: Seedha Khaate Mein (straight into the account) | H87: Centre | I87: IN | J87: India-wide (Centre) | K87: UPA | M87: ₹4,000 for pregnant and lactating women, in 53 pilot districts | T87: A 2015 pledge to widen it to 200 districts was unmet by January 2017, when the nationwide PMMVY began. | V87: distribution | W87: hdb015 | X87: https://occult-kranti.github.io/fact-duel/hisaab/#/q/hdb015 | Y87: The Indian Express — Maternity benefit scheme: what PM Modi said, where things stand now (5 Jan 2017) | Z87: https://indianexpress.com/article/explained/maternity-benefit-scheme-what-pm-modi-said-where-things-stand-now-4459269/
A88: up-garib-arthik-madad-2010 | B88: 2010-11 | D88: 2010 | E88: Mahamaya Garib Arthik Madad Yojana | F88: distribution | G88: Seedha Khaate Mein (straight into the account) | H88: State | I88: UP | J88: Uttar Pradesh | K88: BSP | L88: Mayawati (Chief Minister, Uttar Pradesh, BSP) | M88: ₹300 a month to BPL families, paid to the woman head | N88: About 31 lakh people | O88: ₹535 crore (first phase) | T88: Launched in all 72 districts at once; the first ₹1,800 instalment covered Oct 2010–Mar 2011. | V88: distribution | W88: hdb108 | X88: https://occult-kranti.github.io/fact-duel/hisaab/#/q/hdb108 | Y88: The Hindu — Mayawati launches welfare scheme for poor (2 Nov 2010) | Z88: https://www.thehindu.com/news/national/other-states/Mayawati-launches-welfare-scheme-for-poor/article15672368.ece
A89: kl-karunya-benevolent-fund-2011 | B89: 2011 | D89: 2011 | E89: Karunya Benevolent Fund | F89: distribution | G89: Seedha Khaate Mein (straight into the account) | H89: State | I89: KL | J89: Kerala | K89: UDF | L89: K.M. Mani (Finance Minister, Kerala, Kerala Congress (M)) | M89: Lottery profits pay poor patients’ treatment for cancer, heart and kidney disease | N89: Nearly 1.5 lakh patients | O89: About ₹1,400 crore (claimed) | T89: Folded into the Karunya Arogya Suraksha Padhathi insurance from April 2019. | V89: distribution | W89: hdb405 | X89: https://occult-kranti.github.io/fact-duel/hisaab/#/q/hdb405 | Y89: The New Indian Express — Legacy lingers post KM Mani’s death (9 Apr 2019) | Z89: https://www.newindianexpress.com/states/kerala/2019/Apr/09/legacy-lingers-post-km-manis-death-1962419.html
A90: kl-rice-2-apl-2011 | B90: 2011 | D90: 2011 | E90: ₹2 rice for APL card holders (Kerala) | F90: pre-election | G90: Chunav Se Pehle (before the vote) | H90: State | I90: KL | J90: Kerala | K90: LDF | L90: C. Divakaran (Food and Civil Supplies Minister, Kerala, CPI) | M90: 6–10 kg of rice a month at ₹2 a kg for above-poverty-line cards | O90: ₹250 crore in the budget | P90: Kerala Assembly 2011 | Q90: 2011-04 | S90: UDF won 72 of 140; LDF 68 | T90: The EC held it up during the poll; the UDF won 72 of 140 to the LDF’s 68. | V90: distribution; pre-election | W90: hpe109 | X90: https://occult-kranti.github.io/fact-duel/hisaab/#/q/hpe109 | Y90: The Hindu — Rice at Rs. 2 a kg in a day or two (19 Apr 2011) | Z90: https://www.thehindu.com/news/national/kerala/Rice-at-Rs.-2-a-kg-in-a-day-or-two/article14689272.ece
A91: mz-nlup-2011 | B91: 2011-01 | D91: 2011 | E91: New Land Use Policy | F91: distribution | G91: Seedha Khaate Mein (straight into the account) | H91: State | I91: MZ | J91: Mizoram | K91: INC | L91: Lalthanhawla (Chief Minister, Mizoram, INC) | M91: ₹1.26 lakh per beneficiary over five years to move farmers off jhum cultivation | N91: 1.2 lakh farmers | O91: ₹2,873.13 crore | T91: The Congress was re-elected in 2013 with 34 of 40 seats, then fell to five in 2018. | V91: distribution | W91: hdb325 | X91: https://occult-kranti.github.io/fact-duel/hisaab/#/q/hdb325 | Y91: Frontline — Playing the Piper (27 Nov 2013) | Z91: https://frontline.thehindu.com/politics/playing-the-piper/article5389646.ece
A92: up-mayawati-birthday-projects-2011 | B92: 2011-01 | D92: 2011 | E92: Mayawati’s birthday projects | F92: pre-election | G92: Chunav Se Pehle (before the vote) | H92: State | I92: UP | J92: Uttar Pradesh | K92: BSP | L92: Mayawati (Chief Minister, Uttar Pradesh, BSP) | M92: 699 projects and schemes, a 10% DA rise, mobile hospital vans and a public-services law | O92: More than ₹4,000 crore | P92: UP Assembly 2012 | Q92: 2012-02 | R92: 389 | S92: SP won 224 of 403 seats; the BSP lost power | T92: The SP won 224 of 403 seats in 2012, ending BSP rule. | V92: pre-election | W92: hpe204 | X92: https://occult-kranti.github.io/fact-duel/hisaab/#/q/hpe204 | Y92: India Today — Maya gifts 699 projects on b'day (16 Jan 2011) | Z92: https://www.indiatoday.in/india/north/story/up-mayawati-gifts-699-welfare-schemes-projects-on-bday-126665-2011-01-15
A93: wb-iit-kharagpur-grant-2011 | B93: 2011-02 | D93: 2011 | E93: Budget 2011-12: IIT Kharagpur grant | F93: pre-election | G93: Chunav Se Pehle (before the vote) | H93: Centre | I93: WB | J93: West Bengal | K93: UPA | L93: Pranab Mukherjee (Union Finance Minister, INC) | M93: ₹200 crore one-time grant to IIT Kharagpur, plus grants to Kolkata institutions | P93: West Bengal Assembly 2011 | Q93: 2011-04 | S93: Trinamool Congress won 184 of 294 seats; Left Front fell to 61, ending 34 years in power | T93: The TMC won 184 of 294 seats, ending 34 years of Left rule. No cited source ties the result to the budget. | V93: pre-election | W93: hpe013 | X93: https://occult-kranti.github.io/fact-duel/hisaab/#/q/hpe013 | Y93: indiabudget.gov.in — Budget Speech 2011-12, Pranab Mukherjee (28 Feb 2011) | Z93: https://www.indiabudget.gov.in/budget2011-2012/ub2011-12/bs/bs.pdf
A94: tn-mixies-grinders-fans-2011 | B94: 2011-06 | D94: 2011 | E94: Mixers, grinders and fans | F94: distribution | G94: Seedha Khaate Mein (straight into the account) | H94: State | I94: TN | J94: Tamil Nadu | K94: AIADMK | L94: J. Jayalalithaa (Chief Minister, Tamil Nadu, AIADMK) | M94: A mixer, a grinder and a fan for women, in phases | N94: About 1.83 crore women (25 lakh packages in 2011-12) | T94: The SC held in 2013 that such promises are not a corrupt practice; in August 2022 it said a three-judge bench would reconsider that. | V94: distribution; pre-election | W94: hdb211; hpe113 | X94: https://occult-kranti.github.io/fact-duel/hisaab/#/q/hdb211 https://occult-kranti.github.io/fact-duel/hisaab/#/q/hpe113 | Y94: The Indian Express — A little bit more: How Jayalalithaa’s freebies compare to what she’s offered before (6 May 2016) | Z94: https://indianexpress.com/article/india/india-news-india/a-little-bit-more-how-ammas-freebies-compare-to-what-shes-offered-before-2787325/
A95: sk-earthquake-central-aid-2011 | B95: 2011-09 | D95: 2011 | E95: Sikkim earthquake central aid | F95: relief | G95: Rahat Kosh (the relief fund) | H95: Centre | I95: SK | J95: Sikkim | K95: UPA | L95: Manmohan Singh (Prime Minister, INC) | M95: ₹1,000 crore for relief and rehabilitation | T95: Against a state damage estimate of about ₹1 lakh crore; an expert team on quake-safe rebuilding was to follow. | V95: relief | W95: hrf014 | X95: https://occult-kranti.github.io/fact-duel/hisaab/#/q/hrf014 | Y95: The Hindu — Rs.1,000-crore Central aid for quake-hit Sikkim (29 Sep 2011) | Z95: https://www.thehindu.com/news/national/rs1000crore-central-aid-for-quakehit-sikkim/article2497796.ece
A96: tn-free-laptops-2011 | B96: 2011-09 | D96: 2011 | E96: Free laptop scheme (Tamil Nadu) | F96: distribution | G96: Seedha Khaate Mein (straight into the account) | H96: State | I96: TN | J96: Tamil Nadu | K96: AIADMK | L96: J. Jayalalithaa (Chief Minister, Tamil Nadu, AIADMK) | M96: Free laptops for Class 12 and college students | N96: 51.67 lakh laptops by 2019 | O96: ₹6,456 crore initial; ₹7,257.61 crore by 2019 | T96: Halted in Covid and discontinued in 2021; the DMK revived laptops or tablets in its 2025-26 budget. | V96: distribution | W96: hdb212 | X96: https://occult-kranti.github.io/fact-duel/hisaab/#/q/hdb212 | Y96: The New Indian Express — 100 percentage free laptops distributed to all (4 Feb 2016) | Z96: https://www.newindianexpress.com/states/tamil-nadu/2016/Feb/04/100-percentage-free-laptops-distributed-to-all-888402.html
A97: rj-free-medicines-2011 | B97: 2011-10 | D97: 2011 | E97: Mukhyamantri Nishulk Dawa Yojana | F97: distribution | G97: Seedha Khaate Mein (straight into the account) | H97: State | I97: RJ | J97: Rajasthan | K97: INC | L97: Ashok Gehlot (Chief Minister, Rajasthan, INC) | M97: Free essential medicines at government health centres | N97: 52.4 crore beneficiary visits (Oct 2011–Dec 2017) | T97: It ran through the BJP’s 2013–18 term; the 2019 budget widened it to 712 medicines and 90 tests. | V97: distribution | W97: hdb109 | X97: https://occult-kranti.github.io/fact-duel/hisaab/#/q/hdb109 | Y97: The Indian Express — Explained: What is Rajasthan’s free medicine scheme (13 Jul 2019) | Z97: https://indianexpress.com/article/explained/explained-rajasthan-free-medicine-scheme-5827614/
A98: mh-drought-fodder-camps-2012 | B98: 2012 | D98: 2012 | E98: Drought fodder camps (Maharashtra) | F98: relief | G98: Rahat Kosh (the relief fund) | H98: State | I98: MH | J98: Maharashtra | K98: INC | L98: Prithviraj Chavan (Chief Minister, Maharashtra, INC) | M98: 553 fodder camps for 4.52 lakh cattle; water tankers to 1,663 villages | O98: ₹749.29 crore for camps; ₹2,000 crore on relief | T98: Down To Earth argued villages with the most sugarcane were among the worst hit for drinking water. | V98: relief | W98: hrf113 | X98: https://occult-kranti.github.io/fact-duel/hisaab/#/q/hrf113 | Y98: Down To Earth — Drought of equity (15 Mar 2013) | Z98: https://www.downtoearth.org.in/environment/drought-of-equity-40606
A99: up-free-laptops-2012 | B99: 2012 | D99: 2012 | E99: Free laptops (UP, 2012–14) | F99: distribution | G99: Seedha Khaate Mein (straight into the account) | H99: State | I99: UP | J99: Uttar Pradesh | K99: SP | L99: Akhilesh Yadav (Chief Minister, Uttar Pradesh, SP) | M99: Free laptops for Class 12 passouts | N99: 14.35 lakh laptops handed out | O99: ₹2,822.71 crore | T99: CAG (2015): 4.55 lakh eligible students left out, ₹598.33 crore unspent; the tablet plan was dropped. | V99: distribution | W99: hdb111 | X99: https://occult-kranti.github.io/fact-duel/hisaab/#/q/hdb111 | Y99: The Indian Express — Free laptops: CAG punches holes, says excessively funded yet short of target (27 Mar 2015) | Z99: https://indianexpress.com/article/cities/lucknow/free-laptops-cag-punches-holes-says-excessively-funded-yet-short-of-target/
A100: tn-cyclone-thane-2012 | B100: 2012-01 | D100: 2012 | E100: Cyclone Thane: interim central relief | F100: relief | G100: Rahat Kosh (the relief fund) | H100: Centre | I100: TN | J100: Tamil Nadu | K100: UPA | L100: Manmohan Singh (Prime Minister, INC) | M100: ₹500 crore for Tamil Nadu and ₹125 crore for Puducherry | T100: Against about ₹5,250 crore sought; Cuddalore alone accounted for over ₹4,000 crore of losses. | V100: relief | W100: hrf206 | X100: https://occult-kranti.github.io/fact-duel/hisaab/#/q/hrf206 | Y100: The Hindu — Rs. 500-crore cyclone relief from Centre (10 Jan 2012) | Z100: https://www.thehindu.com/news/national/tamil-nadu/rs-500crore-cyclone-relief-from-centre/article2790513.ece
...

Sheet By year
A1: Year | B1: Seedha Khaate Mein (distribution) | C1: Rahat Kosh (relief) | D1: Chunav Se Pehle (pre-election) | E1: All measures | F1: Centre | G1: State | H1: Named the poll it preceded
A2: 2000 | B2: =COUNTIFS(Ledger!$D$2:$D$390,$A2,Ledger!$F$2:$F$390,"distribution") -> 2 | C2: =COUNTIFS(Ledger!$D$2:$D$390,$A2,Ledger!$F$2:$F$390,"relief") -> 3 | D2: =COUNTIFS(Ledger!$D$2:$D$390,$A2,Ledger!$F$2:$F$390,"pre-election") -> 1 | E2: =SUM(B2:D2) -> 6 | F2: =COUNTIFS(Ledger!$D$2:$D$390,$A2,Ledger!$H$2:$H$390,"Centre") -> 4 | G2: =COUNTIFS(Ledger!$D$2:$D$390,$A2,Ledger!$H$2:$H$390,"State") -> 2 | H2: =COUNTIFS(Ledger!$D$2:$D$390,$A2,Ledger!$P$2:$P$390,"<>") -> 1
A3: 2001 | B3: =COUNTIFS(Ledger!$D$2:$D$390,$A3,Ledger!$F$2:$F$390,"distribution") -> 3 | C3: =COUNTIFS(Ledger!$D$2:$D$390,$A3,Ledger!$F$2:$F$390,"relief") -> 3 | D3: =COUNTIFS(Ledger!$D$2:$D$390,$A3,Ledger!$F$2:$F$390,"pre-election") -> 0 | E3: =SUM(B3:D3) -> 6 | F3: =COUNTIFS(Ledger!$D$2:$D$390,$A3,Ledger!$H$2:$H$390,"Centre") -> 3 | G3: =COUNTIFS(Ledger!$D$2:$D$390,$A3,Ledger!$H$2:$H$390,"State") -> 3 | H3: =COUNTIFS(Ledger!$D$2:$D$390,$A3,Ledger!$P$2:$P$390,"<>") -> 0
A4: 2002 | B4: =COUNTIFS(Ledger!$D$2:$D$390,$A4,Ledger!$F$2:$F$390,"distribution") -> 4 | C4: =COUNTIFS(Ledger!$D$2:$D$390,$A4,Ledger!$F$2:$F$390,"relief") -> 3 | D4: =COUNTIFS(Ledger!$D$2:$D$390,$A4,Ledger!$F$2:$F$390,"pre-election") -> 0 | E4: =SUM(B4:D4) -> 7 | F4: =COUNTIFS(Ledger!$D$2:$D$390,$A4,Ledger!$H$2:$H$390,"Centre") -> 1 | G4: =COUNTIFS(Ledger!$D$2:$D$390,$A4,Ledger!$H$2:$H$390,"State") -> 6 | H4: =COUNTIFS(Ledger!$D$2:$D$390,$A4,Ledger!$P$2:$P$390,"<>") -> 1
A5: 2003 | B5: =COUNTIFS(Ledger!$D$2:$D$390,$A5,Ledger!$F$2:$F$390,"distribution") -> 3 | C5: =COUNTIFS(Ledger!$D$2:$D$390,$A5,Ledger!$F$2:$F$390,"relief") -> 2 | D5: =COUNTIFS(Ledger!$D$2:$D$390,$A5,Ledger!$F$2:$F$390,"pre-election") -> 2 | E5: =SUM(B5:D5) -> 7 | F5: =COUNTIFS(Ledger!$D$2:$D$390,$A5,Ledger!$H$2:$H$390,"Centre") -> 3 | G5: =COUNTIFS(Ledger!$D$2:$D$390,$A5,Ledger!$H$2:$H$390,"State") -> 4 | H5: =COUNTIFS(Ledger!$D$2:$D$390,$A5,Ledger!$P$2:$P$390,"<>") -> 2
A6: 2004 | B6: =COUNTIFS(Ledger!$D$2:$D$390,$A6,Ledger!$F$2:$F$390,"distribution") -> 3 | C6: =COUNTIFS(Ledger!$D$2:$D$390,$A6,Ledger!$F$2:$F$390,"relief") -> 3 | D6: =COUNTIFS(Ledger!$D$2:$D$390,$A6,Ledger!$F$2:$F$390,"pre-election") -> 8 | E6: =SUM(B6:D6) -> 14 | F6: =COUNTIFS(Ledger!$D$2:$D$390,$A6,Ledger!$H$2:$H$390,"Centre") -> 8 | G6: =COUNTIFS(Ledger!$D$2:$D$390,$A6,Ledger!$H$2:$H$390,"State") -> 6 | H6: =COUNTIFS(Ledger!$D$2:$D$390,$A6,Ledger!$P$2:$P$390,"<>") -> 9
A7: 2005 | B7: =COUNTIFS(Ledger!$D$2:$D$390,$A7,Ledger!$F$2:$F$390,"distribution") -> 3 | C7: =COUNTIFS(Ledger!$D$2:$D$390,$A7,Ledger!$F$2:$F$390,"relief") -> 6 | D7: =COUNTIFS(Ledger!$D$2:$D$390,$A7,Ledger!$F$2:$F$390,"pre-election") -> 1 | E7: =SUM(B7:D7) -> 10 | F7: =COUNTIFS(Ledger!$D$2:$D$390,$A7,Ledger!$H$2:$H$390,"Centre") -> 4 | G7: =COUNTIFS(Ledger!$D$2:$D$390,$A7,Ledger!$H$2:$H$390,"State") -> 6 | H7: =COUNTIFS(Ledger!$D$2:$D$390,$A7,Ledger!$P$2:$P$390,"<>") -> 1
A8: 2006 | B8: =COUNTIFS(Ledger!$D$2:$D$390,$A8,Ledger!$F$2:$F$390,"distribution") -> 5 | C8: =COUNTIFS(Ledger!$D$2:$D$390,$A8,Ledger!$F$2:$F$390,"relief") -> 1 | D8: =COUNTIFS(Ledger!$D$2:$D$390,$A8,Ledger!$F$2:$F$390,"pre-election") -> 0 | E8: =SUM(B8:D8) -> 6 | F8: =COUNTIFS(Ledger!$D$2:$D$390,$A8,Ledger!$H$2:$H$390,"Centre") -> 1 | G8: =COUNTIFS(Ledger!$D$2:$D$390,$A8,Ledger!$H$2:$H$390,"State") -> 5 | H8: =COUNTIFS(Ledger!$D$2:$D$390,$A8,Ledger!$P$2:$P$390,"<>") -> 0
A9: 2007 | B9: =COUNTIFS(Ledger!$D$2:$D$390,$A9,Ledger!$F$2:$F$390,"distribution") -> 3 | C9: =COUNTIFS(Ledger!$D$2:$D$390,$A9,Ledger!$F$2:$F$390,"relief") -> 1 | D9: =COUNTIFS(Ledger!$D$2:$D$390,$A9,Ledger!$F$2:$F$390,"pre-election") -> 0 | E9: =SUM(B9:D9) -> 4 | F9: =COUNTIFS(Ledger!$D$2:$D$390,$A9,Ledger!$H$2:$H$390,"Centre") -> 1 | G9: =COUNTIFS(Ledger!$D$2:$D$390,$A9,Ledger!$H$2:$H$390,"State") -> 3 | H9: =COUNTIFS(Ledger!$D$2:$D$390,$A9,Ledger!$P$2:$P$390,"<>") -> 0
A10: 2008 | B10: =COUNTIFS(Ledger!$D$2:$D$390,$A10,Ledger!$F$2:$F$390,"distribution") -> 1 | C10: =COUNTIFS(Ledger!$D$2:$D$390,$A10,Ledger!$F$2:$F$390,"relief") -> 1 | D10: =COUNTIFS(Ledger!$D$2:$D$390,$A10,Ledger!$F$2:$F$390,"pre-election") -> 11 | E10: =SUM(B10:D10) -> 13 | F10: =COUNTIFS(Ledger!$D$2:$D$390,$A10,Ledger!$H$2:$H$390,"Centre") -> 6 | G10: =COUNTIFS(Ledger!$D$2:$D$390,$A10,Ledger!$H$2:$H$390,"State") -> 7 | H10: =COUNTIFS(Ledger!$D$2:$D$390,$A10,Ledger!$P$2:$P$390,"<>") -> 11
A11: 2009 | B11: =COUNTIFS(Ledger!$D$2:$D$390,$A11,Ledger!$F$2:$F$390,"distribution") -> 2 | C11: =COUNTIFS(Ledger!$D$2:$D$390,$A11,Ledger!$F$2:$F$390,"relief") -> 4 | D11: =COUNTIFS(Ledger!$D$2:$D$390,$A11,Ledger!$F$2:$F$390,"pre-election") -> 4 | E11: =SUM(B11:D11) -> 10 | F11: =COUNTIFS(Ledger!$D$2:$D$390,$A11,Ledger!$H$2:$H$390,"Centre") -> 3 | G11: =COUNTIFS(Ledger!$D$2:$D$390,$A11,Ledger!$H$2:$H$390,"State") -> 7 | H11: =COUNTIFS(Ledger!$D$2:$D$390,$A11,Ledger!$P$2:$P$390,"<>") -> 4
A12: 2010 | B12: =COUNTIFS(Ledger!$D$2:$D$390,$A12,Ledger!$F$2:$F$390,"distribution") -> 2 | C12: =COUNTIFS(Ledger!$D$2:$D$390,$A12,Ledger!$F$2:$F$390,"relief") -> 2 | D12: =COUNTIFS(Ledger!$D$2:$D$390,$A12,Ledger!$F$2:$F$390,"pre-election") -> 0 | E12: =SUM(B12:D12) -> 4 | F12: =COUNTIFS(Ledger!$D$2:$D$390,$A12,Ledger!$H$2:$H$390,"Centre") -> 2 | G12: =COUNTIFS(Ledger!$D$2:$D$390,$A12,Ledger!$H$2:$H$390,"State") -> 2 | H12: =COUNTIFS(Ledger!$D$2:$D$390,$A12,Ledger!$P$2:$P$390,"<>") -> 0
A13: 2011 | B13: =COUNTIFS(Ledger!$D$2:$D$390,$A13,Ledger!$F$2:$F$390,"distribution") -> 5 | C13: =COUNTIFS(Ledger!$D$2:$D$390,$A13,Ledger!$F$2:$F$390,"relief") -> 1 | D13: =COUNTIFS(Ledger!$D$2:$D$390,$A13,Ledger!$F$2:$F$390,"pre-election") -> 3 | E13: =SUM(B13:D13) -> 9 | F13: =COUNTIFS(Ledger!$D$2:$D$390,$A13,Ledger!$H$2:$H$390,"Centre") -> 2 | G13: =COUNTIFS(Ledger!$D$2:$D$390,$A13,Ledger!$H$2:$H$390,"State") -> 7 | H13: =COUNTIFS(Ledger!$D$2:$D$390,$A13,Ledger!$P$2:$P$390,"<>") -> 3
... A28: 2026 | B28: =COUNTIFS(Ledger!$D$2:$D$390,$A28,Ledger!$F$2:$F$390,"distribution") -> 10 | C28: =COUNTIFS(Ledger!$D$2:$D$390,$A28,Ledger!$F$2:$F$390,"relief") -> 1 | D28: =COUNTIFS(Ledger!$D$2:$D$390,$A28,Ledger!$F$2:$F$390,"pre-election") -> 7 | E28: =SUM(B28:D28) -> 18 | F28: =COUNTIFS(Ledger!$D$2:$D$390,$A28,Ledger!$H$2:$H$390,"Centre") -> 2 | G28: =COUNTIFS(Ledger!$D$2:$D$390,$A28,Ledger!$H$2:$H$390,"State") -> 16 | H28: =COUNTIFS(Ledger!$D$2:$D$390,$A28,Ledger!$P$2:$P$390,"<>") -> 7
A29: Total | B29: =SUM(B2:B28) -> 137 | C29: =SUM(C2:C28) -> 95 | D29: =SUM(D2:D28) -> 157 | E29: =SUM(E2:E28) -> 389 | F29: =SUM(F2:F28) -> 128 | G29: =SUM(G2:G28) -> 261 | H29: =SUM(H2:H28) -> 164
A31: Check | B31: =COUNTA(Ledger!$A$2:$A$390) -> 389 | C31: rows on the Ledger sheet; equals the All measures total above.
